{"version": 0.6, "generator": "Overpass API 0.7.57 93a4d346", "osm3s": {"timestamp_osm_base": "2021-11-29T22:03:09Z", "copyright": "The data included in this document is from www.openstreetmap.org. The data is made available under ODbL."}, "elements": [{"type": "node", "id": 178053836, "lat": 37.8272562, "lon": -107.6297749}, {"type": "node", "id": 178056227, "lat": 37.7890143, "lon": -107.6731801}, {"type": "node", "id": 178057632, "lat": 37.8174615, "lon": -107.7008245}, {"type": "node", "id": 330098621, "lat": 37.8036305, "lon": -107.6739262}, {"type": "node", "id": 330098622, "lat": 37.8035782, "lon": -107.6737076}, {"type": "node", "id": 330098623, "lat": 37.8035605, "lon": -107.673563}, {"type": "node", "id": 330098625, "lat": 37.8035498, "lon": -107.6734046}, {"type": "node", "id": 330098630, "lat": 37.8035421, "lon": -107.6729507}, {"type": "node", "id": 330098632, "lat": 37.8035739, "lon": -107.6726628}, {"type": "node", "id": 330098635, "lat": 37.8036284, "lon": -107.6723829}, {"type": "node", "id": 330098636, "lat": 37.8036682, "lon": -107.6722382}, {"type": "node", "id": 330098638, "lat": 37.80373, "lon": -107.6720464}, {"type": "node", "id": 330098640, "lat": 37.8038976, "lon": -107.6716855}, {"type": "node", "id": 330098641, "lat": 37.8040903, "lon": -107.6714193}, {"type": "node", "id": 330098646, "lat": 37.8043419, "lon": -107.6711252, "tags": {"created_by": "Merkaartor 0.12"}}, {"type": "node", "id": 330098653, "lat": 37.8044754, "lon": -107.6709965, "tags": {"created_by": "Merkaartor 0.12"}}, {"type": "node", "id": 330098658, "lat": 37.8046923, "lon": -107.6709125}, {"type": "node", "id": 330098661, "lat": 37.8049611, "lon": -107.6709154}, {"type": "node", "id": 330098663, "lat": 37.8051142, "lon": -107.6709599}, {"type": "node", "id": 330098664, "lat": 37.8052532, "lon": -107.671026, "tags": {"created_by": "Merkaartor 0.12"}}, {"type": "node", "id": 330098667, "lat": 37.8054185, "lon": -107.6711386, "tags": {"created_by": "Merkaartor 0.12"}}, {"type": "node", "id": 330098669, "lat": 37.8056042, "lon": -107.6713351}, {"type": "node", "id": 330098670, "lat": 37.8056918, "lon": -107.6715195, "tags": {"created_by": "Merkaartor 0.12"}}, {"type": "node", "id": 330098680, "lat": 37.8055774, "lon": -107.6699879, "tags": {"created_by": "Merkaartor 0.12"}}, {"type": "node", "id": 330098681, "lat": 37.8057088, "lon": -107.6698619, "tags": {"created_by": "Merkaartor 0.12"}}, {"type": "node", "id": 330098683, "lat": 37.8058212, "lon": -107.6697573, "tags": {"created_by": "Merkaartor 0.12"}}, {"type": "node", "id": 330098685, "lat": 37.8065591, "lon": -107.6690796}, {"type": "node", "id": 330098689, "lat": 37.8055817, "lon": -107.671093, "tags": {"created_by": "Merkaartor 0.12"}}, {"type": "node", "id": 330098691, "lat": 37.8055626, "lon": -107.6708811, "tags": {"created_by": "Merkaartor 0.12"}}, {"type": "node", "id": 330098692, "lat": 37.8055669, "lon": -107.6706665, "tags": {"created_by": "Merkaartor 0.12"}}, {"type": "node", "id": 330098693, "lat": 37.8055859, "lon": -107.6704895, "tags": {"created_by": "Merkaartor 0.12"}}, {"type": "node", "id": 330098694, "lat": 37.8056156, "lon": -107.6703259, "tags": {"created_by": "Merkaartor 0.12"}}, {"type": "node", "id": 330098702, "lat": 37.8056177, "lon": -107.6701328, "tags": {"created_by": "Merkaartor 0.12"}}, {"type": "node", "id": 330098703, "lat": 37.8031064, "lon": -107.6695588, "tags": {"created_by": "Merkaartor 0.12"}}, {"type": "node", "id": 330098704, "lat": 37.8043547, "lon": -107.668392, "tags": {"created_by": "Merkaartor 0.12"}}, {"type": "node", "id": 330098705, "lat": 37.8045538, "lon": -107.6683008, "tags": {"created_by": "Merkaartor 0.12"}}, {"type": "node", "id": 330098706, "lat": 37.8046661, "lon": -107.6682955, "tags": {"created_by": "Merkaartor 0.12"}}, {"type": "node", "id": 330098708, "lat": 37.8048547, "lon": -107.6684242, "tags": {"created_by": "Merkaartor 0.12"}}, {"type": "node", "id": 330098709, "lat": 37.8047658, "lon": -107.6683357, "tags": {"created_by": "Merkaartor 0.12"}}, {"type": "node", "id": 330098732, "lat": 37.8062937, "lon": -107.6707095}, {"type": "node", "id": 330098741, "lat": 37.8070608, "lon": -107.6699879, "tags": {"created_by": "Merkaartor 0.12"}}, {"type": "node", "id": 330098752, "lat": 37.8067716, "lon": -107.6714618}, {"type": "node", "id": 330098756, "lat": 37.8074708, "lon": -107.6707578}, {"type": "node", "id": 330098758, "lat": 37.8068797, "lon": -107.6714122}, {"type": "node", "id": 330098762, "lat": 37.8074021, "lon": -107.6708918}, {"type": "node", "id": 330098774, "lat": 37.8074285, "lon": -107.6705941}, {"type": "node", "id": 330764519, "lat": 37.8084171, "lon": -107.6699987, "tags": {"created_by": "Merkaartor 0.12"}}, {"type": "node", "id": 330764520, "lat": 37.8079382, "lon": -107.6691538, "tags": {"created_by": "Merkaartor 0.12"}}, {"type": "node", "id": 330764521, "lat": 37.8074359, "lon": -107.6682606, "tags": {"created_by": "Merkaartor 0.12"}}, {"type": "node", "id": 330764522, "lat": 37.8063764, "lon": -107.6665118}, {"type": "node", "id": 330764524, "lat": 37.8069358, "lon": -107.667405}, {"type": "node", "id": 330764525, "lat": 37.8087682, "lon": -107.6683713}, {"type": "node", "id": 330764526, "lat": 37.8082709, "lon": -107.6675015, "tags": {"created_by": "Merkaartor 0.12"}}, {"type": "node", "id": 330764527, "lat": 37.8073988, "lon": -107.665691}, {"type": "node", "id": 330764528, "lat": 37.8073798, "lon": -107.6658051}, {"type": "node", "id": 330764529, "lat": 37.8073925, "lon": -107.665915}, {"type": "node", "id": 330764530, "lat": 37.807756, "lon": -107.666603, "tags": {"created_by": "Merkaartor 0.12"}}, {"type": "node", "id": 330764542, "lat": 37.8096228, "lon": -107.6675632, "tags": {"created_by": "Merkaartor 0.12"}}, {"type": "node", "id": 330764543, "lat": 37.8091249, "lon": -107.666713, "tags": {"created_by": "Merkaartor 0.12"}}, {"type": "node", "id": 330764544, "lat": 37.8076775, "lon": -107.6641193}, {"type": "node", "id": 330764545, "lat": 37.8077284, "lon": -107.6643218}, {"type": "node", "id": 330764546, "lat": 37.8080865, "lon": -107.6649695, "tags": {"created_by": "Merkaartor 0.12"}}, {"type": "node", "id": 330764547, "lat": 37.8085993, "lon": -107.6658037, "tags": {"created_by": "Merkaartor 0.12"}}, {"type": "node", "id": 330764548, "lat": 37.8075037, "lon": -107.6655248, "tags": {"created_by": "Merkaartor 0.12"}}, {"type": "node", "id": 330764549, "lat": 37.8099492, "lon": -107.6659351, "tags": {"created_by": "Merkaartor 0.12"}}, {"type": "node", "id": 330764550, "lat": 37.809447, "lon": -107.6650527, "tags": {"created_by": "Merkaartor 0.12"}}, {"type": "node", "id": 330764551, "lat": 37.808932, "lon": -107.6641836, "tags": {"created_by": "Merkaartor 0.12"}}, {"type": "node", "id": 330764552, "lat": 37.8084351, "lon": -107.663328}, {"type": "node", "id": 330764553, "lat": 37.8079339, "lon": -107.6624965, "tags": {"created_by": "Merkaartor 0.12"}}, {"type": "node", "id": 330764554, "lat": 37.8114601, "lon": -107.6685208}, {"type": "node", "id": 330764555, "lat": 37.8119348, "lon": -107.6693442, "tags": {"created_by": "Merkaartor 0.12"}}, {"type": "node", "id": 330764556, "lat": 37.810977, "lon": -107.6676383, "tags": {"created_by": "Merkaartor 0.12"}}, {"type": "node", "id": 330764557, "lat": 37.8104726, "lon": -107.6667961, "tags": {"created_by": "Merkaartor 0.12"}}, {"type": "node", "id": 330764558, "lat": 37.8116805, "lon": -107.668443}, {"type": "node", "id": 330764559, "lat": 37.8120598, "lon": -107.6680836, "tags": {"created_by": "Merkaartor 0.12"}}, {"type": "node", "id": 330764560, "lat": 37.8122124, "lon": -107.667751}, {"type": "node", "id": 330764561, "lat": 37.8108096, "lon": -107.6651412, "tags": {"created_by": "Merkaartor 0.12"}}, {"type": "node", "id": 330764562, "lat": 37.8113224, "lon": -107.666021, "tags": {"created_by": "Merkaartor 0.12"}}, {"type": "node", "id": 330764566, "lat": 37.8118076, "lon": -107.6668819, "tags": {"created_by": "Merkaartor 0.12"}}, {"type": "node", "id": 330764567, "lat": 37.812153, "lon": -107.6674667}, {"type": "node", "id": 330764569, "lat": 37.8092732, "lon": -107.6625555, "tags": {"created_by": "Merkaartor 0.12"}}, {"type": "node", "id": 330764570, "lat": 37.8097882, "lon": -107.6634165, "tags": {"created_by": "Merkaartor 0.12"}}, {"type": "node", "id": 330764571, "lat": 37.8102946, "lon": -107.6642856, "tags": {"created_by": "Merkaartor 0.12"}}, {"type": "node", "id": 330764572, "lat": 37.812651, "lon": -107.6661068, "tags": {"created_by": "Merkaartor 0.12"}}, {"type": "node", "id": 330764573, "lat": 37.812812, "lon": -107.6663857, "tags": {"created_by": "Merkaartor 0.12"}}, {"type": "node", "id": 330764574, "lat": 37.8121361, "lon": -107.6652485, "tags": {"created_by": "Merkaartor 0.12"}}, {"type": "node", "id": 330764575, "lat": 37.8116381, "lon": -107.6644036, "tags": {"created_by": "Merkaartor 0.12"}}, {"type": "node", "id": 330764576, "lat": 37.8111359, "lon": -107.6635211, "tags": {"created_by": "Merkaartor 0.12"}}, {"type": "node", "id": 330764577, "lat": 37.8101346, "lon": -107.6617791}, {"type": "node", "id": 330764578, "lat": 37.8078237, "lon": -107.663894}, {"type": "node", "id": 330764580, "lat": 37.8074412, "lon": -107.6655945}, {"type": "node", "id": 330764581, "lat": 37.8106342, "lon": -107.6626378}, {"type": "node", "id": 330764582, "lat": 37.811234, "lon": -107.6620687}, {"type": "node", "id": 330764583, "lat": 37.8114097, "lon": -107.6619867}, {"type": "node", "id": 330764584, "lat": 37.8137179, "lon": -107.6657607}, {"type": "node", "id": 330764585, "lat": 37.813488, "lon": -107.665345, "tags": {"created_by": "Merkaartor 0.12"}}, {"type": "node", "id": 330764586, "lat": 37.8129837, "lon": -107.6644867, "tags": {"created_by": "Merkaartor 0.12"}}, {"type": "node", "id": 330764587, "lat": 37.8124751, "lon": -107.6636123, "tags": {"created_by": "Merkaartor 0.12"}}, {"type": "node", "id": 330764588, "lat": 37.8119708, "lon": -107.6627674, "tags": {"created_by": "Merkaartor 0.12"}}, {"type": "node", "id": 330764589, "lat": 37.8114962, "lon": -107.6620258}, {"type": "node", "id": 330764590, "lat": 37.8116975, "lon": -107.6623021}, {"type": "node", "id": 330764591, "lat": 37.8146344, "lon": -107.6650835}, {"type": "node", "id": 330764592, "lat": 37.8143313, "lon": -107.6645672, "tags": {"created_by": "Merkaartor 0.12"}}, {"type": "node", "id": 330764593, "lat": 37.8138228, "lon": -107.6637223, "tags": {"created_by": "Merkaartor 0.12"}}, {"type": "node", "id": 330764594, "lat": 37.8133163, "lon": -107.6628318, "tags": {"created_by": "Merkaartor 0.12"}}, {"type": "node", "id": 330764595, "lat": 37.8111592, "lon": -107.6590606, "tags": {"created_by": "Merkaartor 0.12"}}, {"type": "node", "id": 330764596, "lat": 37.811138, "lon": -107.659007, "tags": {"created_by": "Merkaartor 0.12"}}, {"type": "node", "id": 330764597, "lat": 37.8112355, "lon": -107.6592216, "tags": {"created_by": "Merkaartor 0.12"}}, {"type": "node", "id": 330764598, "lat": 37.8117991, "lon": -107.6601952}, {"type": "node", "id": 330764599, "lat": 37.8123267, "lon": -107.6610804}, {"type": "node", "id": 330764600, "lat": 37.8124412, "lon": -107.6612869, "tags": {"created_by": "Merkaartor 0.12"}}, {"type": "node", "id": 330764601, "lat": 37.8125217, "lon": -107.661429, "tags": {"created_by": "Merkaartor 0.12"}}, {"type": "node", "id": 330764602, "lat": 37.8128099, "lon": -107.6619172, "tags": {"created_by": "Merkaartor 0.12"}}, {"type": "node", "id": 330764603, "lat": 37.8110377, "lon": -107.6608244}, {"type": "node", "id": 330764604, "lat": 37.8155688, "lon": -107.6643634}, {"type": "node", "id": 330764605, "lat": 37.8154735, "lon": -107.6642882}, {"type": "node", "id": 330764606, "lat": 37.8151535, "lon": -107.6638215, "tags": {"created_by": "Merkaartor 0.12"}}, {"type": "node", "id": 330764607, "lat": 37.8151958, "lon": -107.6637813, "tags": {"created_by": "Merkaartor 0.12"}}, {"type": "node", "id": 330764608, "lat": 37.8146809, "lon": -107.6629016, "tags": {"created_by": "Merkaartor 0.12"}}, {"type": "node", "id": 330764609, "lat": 37.814166, "lon": -107.6620647, "tags": {"created_by": "Merkaartor 0.12"}}, {"type": "node", "id": 330764612, "lat": 37.8122441, "lon": -107.6587736, "tags": {"created_by": "Merkaartor 0.12"}}, {"type": "node", "id": 330764613, "lat": 37.8126213, "lon": -107.6593879, "tags": {"created_by": "Merkaartor 0.12"}}, {"type": "node", "id": 330764614, "lat": 37.8131426, "lon": -107.6602623, "tags": {"created_by": "Merkaartor 0.12"}}, {"type": "node", "id": 330764615, "lat": 37.8161048, "lon": -107.6629069, "tags": {"created_by": "Merkaartor 0.12"}}, {"type": "node", "id": 330764616, "lat": 37.8157086, "lon": -107.662231, "tags": {"created_by": "Merkaartor 0.12"}}, {"type": "node", "id": 330764617, "lat": 37.8156218, "lon": -107.662168}, {"type": "node", "id": 330764618, "lat": 37.8150602, "lon": -107.6612439, "tags": {"created_by": "Merkaartor 0.12"}}, {"type": "node", "id": 330764619, "lat": 37.8145559, "lon": -107.6603964, "tags": {"created_by": "Merkaartor 0.12"}}, {"type": "node", "id": 330764620, "lat": 37.8139881, "lon": -107.6594951, "tags": {"created_by": "Merkaartor 0.12"}}, {"type": "node", "id": 330764621, "lat": 37.8134541, "lon": -107.6586234, "tags": {"created_by": "Merkaartor 0.12"}}, {"type": "node", "id": 330764622, "lat": 37.8131405, "lon": -107.6580789, "tags": {"created_by": "Merkaartor 0.12"}}, {"type": "node", "id": 330764623, "lat": 37.8156111, "lon": -107.6607156, "tags": {"created_by": "Merkaartor 0.12"}}, {"type": "node", "id": 330764624, "lat": 37.8173095, "lon": -107.6618971}, {"type": "node", "id": 330764625, "lat": 37.8171622, "lon": -107.6619655, "tags": {"created_by": "Merkaartor 0.12"}}, {"type": "node", "id": 330764626, "lat": 37.8187672, "lon": -107.6622713}, {"type": "node", "id": 330764627, "lat": 37.8182969, "lon": -107.6622176}, {"type": "node", "id": 330764628, "lat": 37.8181284, "lon": -107.6621787}, {"type": "node", "id": 330764629, "lat": 37.8174504, "lon": -107.6619065, "tags": {"created_by": "Merkaartor 0.12"}}, {"type": "node", "id": 330764630, "lat": 37.8155285, "lon": -107.6621774, "tags": {"created_by": "Merkaartor 0.12"}}, {"type": "node", "id": 330764631, "lat": 37.8143249, "lon": -107.6578188, "tags": {"created_by": "Merkaartor 0.12"}}, {"type": "node", "id": 330764632, "lat": 37.8140283, "lon": -107.6572931, "tags": {"created_by": "Merkaartor 0.12"}}, {"type": "node", "id": 330764633, "lat": 37.8148398, "lon": -107.6587307, "tags": {"created_by": "Merkaartor 0.12"}}, {"type": "node", "id": 330764634, "lat": 37.8153336, "lon": -107.6596936, "tags": {"created_by": "Merkaartor 0.12"}}, {"type": "node", "id": 330764635, "lat": 37.8152361, "lon": -107.6597821, "tags": {"created_by": "Merkaartor 0.12"}}, {"type": "node", "id": 330764636, "lat": 37.8155794, "lon": -107.6604956, "tags": {"created_by": "Merkaartor 0.12"}}, {"type": "node", "id": 330764637, "lat": 37.8156027, "lon": -107.6594844, "tags": {"created_by": "Merkaartor 0.12"}}, {"type": "node", "id": 330764638, "lat": 37.8166855, "lon": -107.6597526, "tags": {"created_by": "Merkaartor 0.12"}}, {"type": "node", "id": 330764639, "lat": 37.8159925, "lon": -107.6585, "tags": {"created_by": "Merkaartor 0.12"}}, {"type": "node", "id": 330764640, "lat": 37.8156472, "lon": -107.6578912, "tags": {"created_by": "Merkaartor 0.12"}}, {"type": "node", "id": 330764641, "lat": 37.8151704, "lon": -107.6571294, "tags": {"created_by": "Merkaartor 0.12"}}, {"type": "node", "id": 330764643, "lat": 37.8165647, "lon": -107.6571214, "tags": {"created_by": "Merkaartor 0.12"}}, {"type": "node", "id": 330764644, "lat": 37.8160286, "lon": -107.656314, "tags": {"created_by": "Merkaartor 0.12"}}, {"type": "node", "id": 330764645, "lat": 37.8170118, "lon": -107.6565259, "tags": {"created_by": "Merkaartor 0.12"}}, {"type": "node", "id": 330764646, "lat": 37.81641, "lon": -107.6574406, "tags": {"created_by": "Merkaartor 0.12"}}, {"type": "node", "id": 330764647, "lat": 37.8162235, "lon": -107.6578912, "tags": {"created_by": "Merkaartor 0.12"}}, {"type": "node", "id": 330764648, "lat": 37.8155666, "lon": -107.6596936, "tags": {"created_by": "Merkaartor 0.12"}}, {"type": "node", "id": 330764649, "lat": 37.8155582, "lon": -107.6599565, "tags": {"created_by": "Merkaartor 0.12"}}, {"type": "node", "id": 330764650, "lat": 37.8172385, "lon": -107.6599055, "tags": {"created_by": "Merkaartor 0.12"}}, {"type": "node", "id": 330764651, "lat": 37.8169609, "lon": -107.659707, "tags": {"created_by": "Merkaartor 0.12"}}, {"type": "node", "id": 330764652, "lat": 37.8168147, "lon": -107.6597017, "tags": {"created_by": "Merkaartor 0.12"}}, {"type": "node", "id": 330764653, "lat": 37.8158781, "lon": -107.6604876, "tags": {"created_by": "Merkaartor 0.12"}}, {"type": "node", "id": 331024442, "lat": 37.814806, "lon": -107.6614853, "tags": {"created_by": "Merkaartor 0.12"}}, {"type": "node", "id": 331024444, "lat": 37.8149056, "lon": -107.6613888, "tags": {"created_by": "Merkaartor 0.12"}}, {"type": "node", "id": 331050841, "lat": 37.8072558, "lon": -107.6751592, "tags": {"created_by": "Merkaartor 0.12"}}, {"type": "node", "id": 331050882, "lat": 37.807683, "lon": -107.6762164}, {"type": "node", "id": 331050884, "lat": 37.8078047, "lon": -107.6765701, "tags": {"created_by": "Merkaartor 0.12"}}, {"type": "node", "id": 331050887, "lat": 37.8080042, "lon": -107.6772033}, {"type": "node", "id": 331050890, "lat": 37.8082073, "lon": -107.6780453, "tags": {"created_by": "Merkaartor 0.12"}}, {"type": "node", "id": 331050892, "lat": 37.8086373, "lon": -107.6801094}, {"type": "node", "id": 331051212, "lat": 37.8081014, "lon": -107.677584, "tags": {"created_by": "Merkaartor 0.12"}}, {"type": "node", "id": 331058110, "lat": 37.8173586, "lon": -107.6599679}, {"type": "node", "id": 331058113, "lat": 37.8175012, "lon": -107.6599538, "tags": {"created_by": "Merkaartor 0.12"}}, {"type": "node", "id": 331058115, "lat": 37.8176495, "lon": -107.6598358, "tags": {"created_by": "Merkaartor 0.12"}}, {"type": "node", "id": 331058117, "lat": 37.8179567, "lon": -107.659294, "tags": {"created_by": "Merkaartor 0.12"}}, {"type": "node", "id": 331058119, "lat": 37.8180224, "lon": -107.6590586}, {"type": "node", "id": 331058121, "lat": 37.8180528, "lon": -107.6588366}, {"type": "node", "id": 331058123, "lat": 37.8180818, "lon": -107.6584518, "tags": {"created_by": "Merkaartor 0.12"}}, {"type": "node", "id": 331058125, "lat": 37.8180967, "lon": -107.6583566}, {"type": "node", "id": 331058126, "lat": 37.8181814, "lon": -107.6583016, "tags": {"created_by": "Merkaartor 0.12"}}, {"type": "node", "id": 331058127, "lat": 37.8183657, "lon": -107.6584196}, {"type": "node", "id": 331058128, "lat": 37.8184235, "lon": -107.6585293}, {"type": "node", "id": 331058131, "lat": 37.8185119, "lon": -107.6587549, "tags": {"created_by": "Merkaartor 0.12"}}, {"type": "node", "id": 331058133, "lat": 37.8186263, "lon": -107.6589104, "tags": {"created_by": "Merkaartor 0.12"}}, {"type": "node", "id": 331058136, "lat": 37.8190204, "lon": -107.659302, "tags": {"created_by": "Merkaartor 0.12"}}, {"type": "node", "id": 331058138, "lat": 37.8191284, "lon": -107.6594335, "tags": {"created_by": "Merkaartor 0.12"}}, {"type": "node", "id": 331058140, "lat": 37.8192196, "lon": -107.6596561, "tags": {"created_by": "Merkaartor 0.12"}}, {"type": "node", "id": 331058142, "lat": 37.8192958, "lon": -107.6599377, "tags": {"created_by": "Merkaartor 0.12"}}, {"type": "node", "id": 331058144, "lat": 37.8181867, "lon": -107.6574714}, {"type": "node", "id": 331058146, "lat": 37.8181665, "lon": -107.6566922, "tags": {"created_by": "Merkaartor 0.12"}}, {"type": "node", "id": 331058149, "lat": 37.8181559, "lon": -107.6562497, "tags": {"created_by": "Merkaartor 0.12"}}, {"type": "node", "id": 331058151, "lat": 37.8182047, "lon": -107.6559466, "tags": {"created_by": "Merkaartor 0.12"}}, {"type": "node", "id": 331058153, "lat": 37.8183, "lon": -107.6556542, "tags": {"created_by": "Merkaartor 0.12"}}, {"type": "node", "id": 331058155, "lat": 37.818442, "lon": -107.6553407}, {"type": "node", "id": 331058157, "lat": 37.8184872, "lon": -107.6551795}, {"type": "node", "id": 331058159, "lat": 37.818462, "lon": -107.6548349}, {"type": "node", "id": 331058162, "lat": 37.8183491, "lon": -107.6545406}, {"type": "node", "id": 331058166, "lat": 37.8180386, "lon": -107.6542002}, {"type": "node", "id": 331058169, "lat": 37.817899, "lon": -107.6540195}, {"type": "node", "id": 331058171, "lat": 37.8177467, "lon": -107.6536723}, {"type": "node", "id": 331058173, "lat": 37.8176753, "lon": -107.6533724}, {"type": "node", "id": 331058175, "lat": 37.8176818, "lon": -107.6529008}, {"type": "node", "id": 331058177, "lat": 37.8177533, "lon": -107.6524034, "tags": {"created_by": "Merkaartor 0.12"}}, {"type": "node", "id": 331058181, "lat": 37.8178932, "lon": -107.6517516, "tags": {"created_by": "Merkaartor 0.12"}}, {"type": "node", "id": 331058183, "lat": 37.8179049, "lon": -107.6514311}, {"type": "node", "id": 331058189, "lat": 37.8182789, "lon": -107.656416, "tags": {"created_by": "Merkaartor 0.12"}}, {"type": "node", "id": 331058192, "lat": 37.8184462, "lon": -107.6561343, "tags": {"created_by": "Merkaartor 0.12"}}, {"type": "node", "id": 331058195, "lat": 37.8186751, "lon": -107.6558554, "tags": {"created_by": "Merkaartor 0.12"}}, {"type": "node", "id": 331058197, "lat": 37.8189145, "lon": -107.6553726, "tags": {"created_by": "Merkaartor 0.12"}}, {"type": "node", "id": 331058329, "lat": 37.8171474, "lon": -107.6562899, "tags": {"created_by": "Merkaartor 0.12"}}, {"type": "node", "id": 331058333, "lat": 37.8172724, "lon": -107.6560136, "tags": {"created_by": "Merkaartor 0.12"}}, {"type": "node", "id": 331058338, "lat": 37.817355, "lon": -107.6556891, "tags": {"created_by": "Merkaartor 0.12"}}, {"type": "node", "id": 331058340, "lat": 37.8173783, "lon": -107.655335, "tags": {"created_by": "Merkaartor 0.12"}}, {"type": "node", "id": 331058342, "lat": 37.8173719, "lon": -107.6550534, "tags": {"created_by": "Merkaartor 0.12"}}, {"type": "node", "id": 331058345, "lat": 37.8173232, "lon": -107.6546511, "tags": {"created_by": "Merkaartor 0.12"}}, {"type": "node", "id": 331058347, "lat": 37.8173148, "lon": -107.6541468, "tags": {"created_by": "Merkaartor 0.12"}}, {"type": "node", "id": 331058350, "lat": 37.8173783, "lon": -107.6536399, "tags": {"created_by": "Merkaartor 0.12"}}, {"type": "node", "id": 331058357, "lat": 37.8175775, "lon": -107.6525026, "tags": {"created_by": "Merkaartor 0.12"}}, {"type": "node", "id": 331058360, "lat": 37.8181061, "lon": -107.6508315}, {"type": "node", "id": 331058362, "lat": 37.8178063, "lon": -107.659581, "tags": {"created_by": "Merkaartor 0.12"}}, {"type": "node", "id": 331058364, "lat": 37.8182492, "lon": -107.6583177, "tags": {"created_by": "Merkaartor 0.12"}}, {"type": "node", "id": 331058367, "lat": 37.8174652, "lon": -107.6530552, "tags": {"created_by": "Merkaartor 0.12"}}, {"type": "node", "id": 331058368, "lat": 37.8177512, "lon": -107.6518991, "tags": {"created_by": "Merkaartor 0.12"}}, {"type": "node", "id": 331107623, "lat": 37.8037469, "lon": -107.6742776}, {"type": "node", "id": 331107624, "lat": 37.8037969, "lon": -107.6743977}, {"type": "node", "id": 331107625, "lat": 37.8042206, "lon": -107.6751741}, {"type": "node", "id": 331107627, "lat": 37.8037055, "lon": -107.6744389}, {"type": "node", "id": 331107628, "lat": 37.8034997, "lon": -107.6742658}, {"type": "node", "id": 331107631, "lat": 37.8029792, "lon": -107.6736465, "tags": {"created_by": "Merkaartor 0.12"}}, {"type": "node", "id": 331107634, "lat": 37.8027758, "lon": -107.6733541, "tags": {"created_by": "Merkaartor 0.12"}}, {"type": "node", "id": 331107636, "lat": 37.8026507, "lon": -107.6730886, "tags": {"created_by": "Merkaartor 0.12"}}, {"type": "node", "id": 331107638, "lat": 37.8025406, "lon": -107.672764, "tags": {"created_by": "Merkaartor 0.12"}}, {"type": "node", "id": 331107639, "lat": 37.8024494, "lon": -107.6726138, "tags": {"created_by": "Merkaartor 0.12"}}, {"type": "node", "id": 331107641, "lat": 37.8022459, "lon": -107.6724234, "tags": {"created_by": "Merkaartor 0.12"}}, {"type": "node", "id": 331107643, "lat": 37.8018709, "lon": -107.6719728, "tags": {"created_by": "Merkaartor 0.12"}}, {"type": "node", "id": 331107645, "lat": 37.8015657, "lon": -107.6716295, "tags": {"created_by": "Merkaartor 0.12"}}, {"type": "node", "id": 331107647, "lat": 37.8015063, "lon": -107.6714873, "tags": {"created_by": "Merkaartor 0.12"}}, {"type": "node", "id": 331107652, "lat": 37.8014279, "lon": -107.6711708, "tags": {"created_by": "Merkaartor 0.12"}}, {"type": "node", "id": 331107654, "lat": 37.8013431, "lon": -107.6709938, "tags": {"created_by": "Merkaartor 0.12"}}, {"type": "node", "id": 331107656, "lat": 37.8010252, "lon": -107.6705512, "tags": {"created_by": "Merkaartor 0.12"}}, {"type": "node", "id": 331107658, "lat": 37.800665, "lon": -107.6701462, "tags": {"created_by": "Merkaartor 0.12"}}, {"type": "node", "id": 331107660, "lat": 37.800595, "lon": -107.6701167, "tags": {"created_by": "Merkaartor 0.12"}}, {"type": "node", "id": 331107662, "lat": 37.7998299, "lon": -107.6700577, "tags": {"created_by": "Merkaartor 0.12"}}, {"type": "node", "id": 331107663, "lat": 37.7995226, "lon": -107.670106, "tags": {"created_by": "Merkaartor 0.12"}}, {"type": "node", "id": 331107665, "lat": 37.8052638, "lon": -107.6773908, "tags": {"created_by": "Merkaartor 0.12"}}, {"type": "node", "id": 331107666, "lat": 37.806136, "lon": -107.679361}, {"type": "node", "id": 331107667, "lat": 37.8061669, "lon": -107.6794651}, {"type": "node", "id": 331107668, "lat": 37.8061943, "lon": -107.6796472}, {"type": "node", "id": 331107669, "lat": 37.8061819, "lon": -107.6798271}, {"type": "node", "id": 331107670, "lat": 37.8060229, "lon": -107.6800855}, {"type": "node", "id": 331107671, "lat": 37.8059207, "lon": -107.6801374, "tags": {"created_by": "Merkaartor 0.12"}}, {"type": "node", "id": 331107672, "lat": 37.8057936, "lon": -107.6801428, "tags": {"created_by": "Merkaartor 0.12"}}, {"type": "node", "id": 331107673, "lat": 37.8055414, "lon": -107.6799711, "tags": {"created_by": "Merkaartor 0.12"}}, {"type": "node", "id": 331107674, "lat": 37.805232, "lon": -107.6795999}, {"type": "node", "id": 331107675, "lat": 37.8048576, "lon": -107.6792237}, {"type": "node", "id": 331107676, "lat": 37.8044162, "lon": -107.6788961}, {"type": "node", "id": 331107677, "lat": 37.803732, "lon": -107.6784892}, {"type": "node", "id": 331107678, "lat": 37.8035897, "lon": -107.6783816}, {"type": "node", "id": 331107679, "lat": 37.8031936, "lon": -107.6779923}, {"type": "node", "id": 331107688, "lat": 37.8061243, "lon": -107.6799692}, {"type": "node", "id": 331107689, "lat": 37.805658, "lon": -107.6800865, "tags": {"created_by": "Merkaartor 0.12"}}, {"type": "node", "id": 331108705, "lat": 37.7992831, "lon": -107.6700845, "tags": {"created_by": "Merkaartor 0.12"}}, {"type": "node", "id": 331108706, "lat": 37.7989546, "lon": -107.6699826, "tags": {"created_by": "Merkaartor 0.12"}}, {"type": "node", "id": 331108707, "lat": 37.7986028, "lon": -107.669937, "tags": {"created_by": "Merkaartor 0.12"}}, {"type": "node", "id": 331108708, "lat": 37.7982086, "lon": -107.6697707, "tags": {"created_by": "Merkaartor 0.12"}}, {"type": "node", "id": 331108709, "lat": 37.796992, "lon": -107.6694998, "tags": {"created_by": "Merkaartor 0.12"}}, {"type": "node", "id": 331108710, "lat": 37.7963011, "lon": -107.6693845, "tags": {"created_by": "Merkaartor 0.12"}}, {"type": "node", "id": 331108711, "lat": 37.7961548, "lon": -107.6694086, "tags": {"created_by": "Merkaartor 0.12"}}, {"type": "node", "id": 331108712, "lat": 37.7960086, "lon": -107.6695105, "tags": {"created_by": "Merkaartor 0.12"}}, {"type": "node", "id": 331108713, "lat": 37.7955444, "lon": -107.6694864, "tags": {"created_by": "Merkaartor 0.12"}}, {"type": "node", "id": 331108714, "lat": 37.7950264, "lon": -107.6694315}, {"type": "node", "id": 331108715, "lat": 37.7945101, "lon": -107.6693415, "tags": {"created_by": "Merkaartor 0.12"}}, {"type": "node", "id": 331108716, "lat": 37.7940862, "lon": -107.6692289, "tags": {"created_by": "Merkaartor 0.12"}}, {"type": "node", "id": 331108717, "lat": 37.7934037, "lon": -107.669127, "tags": {"created_by": "Merkaartor 0.12"}}, {"type": "node", "id": 331108718, "lat": 37.7930794, "lon": -107.6690384, "tags": {"created_by": "Merkaartor 0.12"}}, {"type": "node", "id": 331108719, "lat": 37.7928569, "lon": -107.6690036, "tags": {"created_by": "Merkaartor 0.12"}}, {"type": "node", "id": 331108720, "lat": 37.7919009, "lon": -107.6689285, "tags": {"created_by": "Merkaartor 0.12"}}, {"type": "node", "id": 331108721, "lat": 37.7914791, "lon": -107.6689526, "tags": {"created_by": "Merkaartor 0.12"}}, {"type": "node", "id": 331108722, "lat": 37.7911994, "lon": -107.6690277, "tags": {"created_by": "Merkaartor 0.12"}}, {"type": "node", "id": 331108723, "lat": 37.7908814, "lon": -107.6691967, "tags": {"created_by": "Merkaartor 0.12"}}, {"type": "node", "id": 331679567, "lat": 37.8169105, "lon": -107.6499604}, {"type": "node", "id": 331679568, "lat": 37.8168083, "lon": -107.6501986, "tags": {"created_by": "Merkaartor 0.12"}}, {"type": "node", "id": 331679569, "lat": 37.8167469, "lon": -107.6504963, "tags": {"created_by": "Merkaartor 0.12"}}, {"type": "node", "id": 331679570, "lat": 37.8167024, "lon": -107.6508826, "tags": {"created_by": "Merkaartor 0.12"}}, {"type": "node", "id": 331679571, "lat": 37.8164057, "lon": -107.6550239, "tags": {"created_by": "Merkaartor 0.12"}}, {"type": "node", "id": 331679573, "lat": 37.8163443, "lon": -107.6554423, "tags": {"created_by": "Merkaartor 0.12"}}, {"type": "node", "id": 331679583, "lat": 37.816344, "lon": -107.6495419}, {"type": "node", "id": 333718019, "lat": 37.8268017, "lon": -107.6309134}, {"type": "node", "id": 333718020, "lat": 37.826207, "lon": -107.6325524, "tags": {"created_by": "Merkaartor 0.12"}}, {"type": "node", "id": 333718021, "lat": 37.825991, "lon": -107.6330968, "tags": {"created_by": "Merkaartor 0.12"}}, {"type": "node", "id": 333718022, "lat": 37.8257918, "lon": -107.6335072, "tags": {"created_by": "Merkaartor 0.12"}}, {"type": "node", "id": 333718023, "lat": 37.8254316, "lon": -107.6341241, "tags": {"created_by": "Merkaartor 0.12"}}, {"type": "node", "id": 333718024, "lat": 37.825205, "lon": -107.6344433, "tags": {"created_by": "Merkaartor 0.12"}}, {"type": "node", "id": 333718025, "lat": 37.8245588, "lon": -107.6352453, "tags": {"created_by": "Merkaartor 0.12"}}, {"type": "node", "id": 333718026, "lat": 37.8242919, "lon": -107.6355216, "tags": {"created_by": "Merkaartor 0.12"}}, {"type": "node", "id": 333718029, "lat": 37.8241012, "lon": -107.6357871, "tags": {"created_by": "Merkaartor 0.12"}}, {"type": "node", "id": 333718031, "lat": 37.8239507, "lon": -107.6360875, "tags": {"created_by": "Merkaartor 0.12"}}, {"type": "node", "id": 333718033, "lat": 37.823849, "lon": -107.6363799, "tags": {"created_by": "Merkaartor 0.12"}}, {"type": "node", "id": 333718036, "lat": 37.8234677, "lon": -107.6378283, "tags": {"created_by": "Merkaartor 0.12"}}, {"type": "node", "id": 333718038, "lat": 37.8225884, "lon": -107.6407841, "tags": {"created_by": "Merkaartor 0.12"}}, {"type": "node", "id": 333718041, "lat": 37.8224146, "lon": -107.6411676, "tags": {"created_by": "Merkaartor 0.12"}}, {"type": "node", "id": 333718043, "lat": 37.8222134, "lon": -107.6414519, "tags": {"created_by": "Merkaartor 0.12"}}, {"type": "node", "id": 333718045, "lat": 37.8220058, "lon": -107.6416638, "tags": {"created_by": "Merkaartor 0.12"}}, {"type": "node", "id": 333718050, "lat": 37.8218129, "lon": -107.6418221, "tags": {"created_by": "Merkaartor 0.12"}}, {"type": "node", "id": 333718051, "lat": 37.8215756, "lon": -107.6419455, "tags": {"created_by": "Merkaartor 0.12"}}, {"type": "node", "id": 333718052, "lat": 37.8207875, "lon": -107.6422593, "tags": {"created_by": "Merkaartor 0.12"}}, {"type": "node", "id": 333718053, "lat": 37.8205099, "lon": -107.6423961, "tags": {"created_by": "Merkaartor 0.12"}}, {"type": "node", "id": 333718054, "lat": 37.8203022, "lon": -107.6425355, "tags": {"created_by": "Merkaartor 0.12"}}, {"type": "node", "id": 333718055, "lat": 37.8200904, "lon": -107.6427367, "tags": {"created_by": "Merkaartor 0.12"}}, {"type": "node", "id": 333718056, "lat": 37.8198764, "lon": -107.6429674, "tags": {"created_by": "Merkaartor 0.12"}}, {"type": "node", "id": 333718057, "lat": 37.8197112, "lon": -107.6432034, "tags": {"created_by": "Merkaartor 0.12"}}, {"type": "node", "id": 333718058, "lat": 37.819512, "lon": -107.643544, "tags": {"created_by": "Merkaartor 0.12"}}, {"type": "node", "id": 333718059, "lat": 37.8188318, "lon": -107.6448583, "tags": {"created_by": "Merkaartor 0.12"}}, {"type": "node", "id": 333718060, "lat": 37.8187005, "lon": -107.6451614, "tags": {"created_by": "Merkaartor 0.12"}}, {"type": "node", "id": 333718061, "lat": 37.8185966, "lon": -107.6455021, "tags": {"created_by": "Merkaartor 0.12"}}, {"type": "node", "id": 333718062, "lat": 37.8185225, "lon": -107.6458293, "tags": {"created_by": "Merkaartor 0.12"}}, {"type": "node", "id": 333718063, "lat": 37.8184737, "lon": -107.6461592, "tags": {"created_by": "Merkaartor 0.12"}}, {"type": "node", "id": 333718064, "lat": 37.8184525, "lon": -107.6465133, "tags": {"created_by": "Merkaartor 0.12"}}, {"type": "node", "id": 333718065, "lat": 37.8184589, "lon": -107.6470229, "tags": {"created_by": "Merkaartor 0.12"}}, {"type": "node", "id": 333718066, "lat": 37.8185267, "lon": -107.6481682, "tags": {"created_by": "Merkaartor 0.12"}}, {"type": "node", "id": 333718067, "lat": 37.8185436, "lon": -107.648592, "tags": {"created_by": "Merkaartor 0.12"}}, {"type": "node", "id": 333718068, "lat": 37.8185436, "lon": -107.6490667, "tags": {"created_by": "Merkaartor 0.12"}}, {"type": "node", "id": 333718069, "lat": 37.8185013, "lon": -107.6494825, "tags": {"created_by": "Merkaartor 0.12"}}, {"type": "node", "id": 333718070, "lat": 37.8184229, "lon": -107.6498633, "tags": {"created_by": "Merkaartor 0.12"}}, {"type": "node", "id": 333719454, "lat": 37.819423, "lon": -107.6602596, "tags": {"created_by": "Merkaartor 0.12"}}, {"type": "node", "id": 333719456, "lat": 37.8195226, "lon": -107.6604393, "tags": {"created_by": "Merkaartor 0.12"}}, {"type": "node", "id": 333719458, "lat": 37.8197324, "lon": -107.6606163, "tags": {"created_by": "Merkaartor 0.12"}}, {"type": "node", "id": 333719459, "lat": 37.8201222, "lon": -107.6608121, "tags": {"created_by": "Merkaartor 0.12"}}, {"type": "node", "id": 333719460, "lat": 37.8202323, "lon": -107.6609033, "tags": {"created_by": "Merkaartor 0.12"}}, {"type": "node", "id": 333719461, "lat": 37.8203256, "lon": -107.6610455, "tags": {"created_by": "Merkaartor 0.12"}}, {"type": "node", "id": 333719462, "lat": 37.8204718, "lon": -107.6613646, "tags": {"created_by": "Merkaartor 0.12"}}, {"type": "node", "id": 333719463, "lat": 37.8207091, "lon": -107.6617938, "tags": {"created_by": "Merkaartor 0.12"}}, {"type": "node", "id": 333719464, "lat": 37.8207409, "lon": -107.6619735, "tags": {"created_by": "Merkaartor 0.12"}}, {"type": "node", "id": 333719465, "lat": 37.8207218, "lon": -107.662577, "tags": {"created_by": "Merkaartor 0.12"}}, {"type": "node", "id": 333719466, "lat": 37.8207514, "lon": -107.6627111, "tags": {"created_by": "Merkaartor 0.12"}}, {"type": "node", "id": 333719467, "lat": 37.8208129, "lon": -107.662856, "tags": {"created_by": "Merkaartor 0.12"}}, {"type": "node", "id": 333719468, "lat": 37.8214951, "lon": -107.6636767, "tags": {"created_by": "Merkaartor 0.12"}}, {"type": "node", "id": 333719469, "lat": 37.8217197, "lon": -107.6639637, "tags": {"created_by": "Merkaartor 0.12"}}, {"type": "node", "id": 333719470, "lat": 37.8218405, "lon": -107.6641032, "tags": {"created_by": "Merkaartor 0.12"}}, {"type": "node", "id": 333719473, "lat": 37.8220524, "lon": -107.6642909, "tags": {"created_by": "Merkaartor 0.12"}}, {"type": "node", "id": 333719474, "lat": 37.8224613, "lon": -107.6645833, "tags": {"created_by": "Merkaartor 0.12"}}, {"type": "node", "id": 333719476, "lat": 37.8227579, "lon": -107.6648891, "tags": {"created_by": "Merkaartor 0.12"}}, {"type": "node", "id": 333719477, "lat": 37.8229973, "lon": -107.6652807, "tags": {"created_by": "Merkaartor 0.12"}}, {"type": "node", "id": 333719478, "lat": 37.8231075, "lon": -107.6654201, "tags": {"created_by": "Merkaartor 0.12"}}, {"type": "node", "id": 333719479, "lat": 37.8232558, "lon": -107.6655543, "tags": {"created_by": "Merkaartor 0.12"}}, {"type": "node", "id": 333719480, "lat": 37.8235418, "lon": -107.6657045, "tags": {"created_by": "Merkaartor 0.12"}}, {"type": "node", "id": 333719481, "lat": 37.8340243, "lon": -107.6731449, "tags": {"created_by": "Merkaartor 0.12"}}, {"type": "node", "id": 333719482, "lat": 37.8339798, "lon": -107.6735928, "tags": {"created_by": "Merkaartor 0.12"}}, {"type": "node", "id": 333719484, "lat": 37.8340285, "lon": -107.6728686, "tags": {"created_by": "Merkaartor 0.12"}}, {"type": "node", "id": 333719485, "lat": 37.8339735, "lon": -107.6725682, "tags": {"created_by": "Merkaartor 0.12"}}, {"type": "node", "id": 333719486, "lat": 37.8338824, "lon": -107.6723027, "tags": {"created_by": "Merkaartor 0.12"}}, {"type": "node", "id": 333719487, "lat": 37.833715, "lon": -107.6721069, "tags": {"created_by": "Merkaartor 0.12"}}, {"type": "node", "id": 333719488, "lat": 37.8326008, "lon": -107.671557, "tags": {"created_by": "Merkaartor 0.12"}}, {"type": "node", "id": 333719489, "lat": 37.8321729, "lon": -107.6714337, "tags": {"created_by": "Merkaartor 0.12"}}, {"type": "node", "id": 333719490, "lat": 37.8316793, "lon": -107.6711547, "tags": {"created_by": "Merkaartor 0.12"}}, {"type": "node", "id": 333719491, "lat": 37.8315055, "lon": -107.6710716, "tags": {"created_by": "Merkaartor 0.12"}}, {"type": "node", "id": 333719493, "lat": 37.8306687, "lon": -107.6708463, "tags": {"created_by": "Merkaartor 0.12"}}, {"type": "node", "id": 333719494, "lat": 37.8304314, "lon": -107.6706907, "tags": {"created_by": "Merkaartor 0.12"}}, {"type": "node", "id": 333719496, "lat": 37.8302429, "lon": -107.670688, "tags": {"created_by": "Merkaartor 0.12"}}, {"type": "node", "id": 333719497, "lat": 37.8298298, "lon": -107.6707658, "tags": {"created_by": "Merkaartor 0.12"}}, {"type": "node", "id": 333719498, "lat": 37.8296073, "lon": -107.6707336, "tags": {"created_by": "Merkaartor 0.12"}}, {"type": "node", "id": 333719499, "lat": 37.8293743, "lon": -107.6706317, "tags": {"created_by": "Merkaartor 0.12"}}, {"type": "node", "id": 333719500, "lat": 37.8287387, "lon": -107.6701393}, {"type": "node", "id": 333719501, "lat": 37.8286704, "lon": -107.6700425}, {"type": "node", "id": 333719502, "lat": 37.8284185, "lon": -107.6695927}, {"type": "node", "id": 333719503, "lat": 37.8282477, "lon": -107.6693675}, {"type": "node", "id": 333719504, "lat": 37.8280568, "lon": -107.6692463}, {"type": "node", "id": 333719506, "lat": 37.8279675, "lon": -107.6692224}, {"type": "node", "id": 333719507, "lat": 37.8277222, "lon": -107.6692103}, {"type": "node", "id": 333719510, "lat": 37.8273371, "lon": -107.6691561}, {"type": "node", "id": 333719513, "lat": 37.8271657, "lon": -107.6690429}, {"type": "node", "id": 333719516, "lat": 37.8270897, "lon": -107.6689731}, {"type": "node", "id": 333719517, "lat": 37.8267007, "lon": -107.6685261, "tags": {"created_by": "Merkaartor 0.12"}}, {"type": "node", "id": 333719527, "lat": 37.8262803, "lon": -107.6678719}, {"type": "node", "id": 333719530, "lat": 37.8260493, "lon": -107.6676596}, {"type": "node", "id": 333719534, "lat": 37.8257265, "lon": -107.6674072}, {"type": "node", "id": 333719536, "lat": 37.8255242, "lon": -107.667296}, {"type": "node", "id": 333719538, "lat": 37.8249797, "lon": -107.6668792}, {"type": "node", "id": 333719539, "lat": 37.8244825, "lon": -107.6664099, "tags": {"created_by": "Merkaartor 0.12"}}, {"type": "node", "id": 333719540, "lat": 37.8237474, "lon": -107.6658037, "tags": {"created_by": "Merkaartor 0.12"}}, {"type": "node", "id": 333719541, "lat": 37.8206286, "lon": -107.6616168, "tags": {"created_by": "Merkaartor 0.12"}}, {"type": "node", "id": 333719542, "lat": 37.8209019, "lon": -107.6630035, "tags": {"created_by": "Merkaartor 0.12"}}, {"type": "node", "id": 333719543, "lat": 37.8210841, "lon": -107.6632261, "tags": {"created_by": "Merkaartor 0.12"}}, {"type": "node", "id": 333719544, "lat": 37.821243, "lon": -107.6634246, "tags": {"created_by": "Merkaartor 0.12"}}, {"type": "node", "id": 333719545, "lat": 37.8226244, "lon": -107.6647255, "tags": {"created_by": "Merkaartor 0.12"}}, {"type": "node", "id": 333721550, "lat": 37.802886, "lon": -107.6777529, "tags": {"created_by": "Merkaartor 0.12"}}, {"type": "node", "id": 333721551, "lat": 37.8025702, "lon": -107.6775813, "tags": {"created_by": "Merkaartor 0.12"}}, {"type": "node", "id": 333721552, "lat": 37.8021022, "lon": -107.6774074}, {"type": "node", "id": 333721553, "lat": 37.8020096, "lon": -107.6773612}, {"type": "node", "id": 333721554, "lat": 37.8018546, "lon": -107.6772527}, {"type": "node", "id": 333721555, "lat": 37.8087655, "lon": -107.6806033}, {"type": "node", "id": 333721556, "lat": 37.808877, "lon": -107.6809099, "tags": {"created_by": "Merkaartor 0.12"}}, {"type": "node", "id": 333721557, "lat": 37.8092352, "lon": -107.6815606}, {"type": "node", "id": 333721558, "lat": 37.8093359, "lon": -107.6817786}, {"type": "node", "id": 333721559, "lat": 37.8094142, "lon": -107.6820218}, {"type": "node", "id": 333721560, "lat": 37.8095281, "lon": -107.6835789}, {"type": "node", "id": 333721561, "lat": 37.8095547, "lon": -107.6838158}, {"type": "node", "id": 333721562, "lat": 37.8098126, "lon": -107.6848656}, {"type": "node", "id": 333721563, "lat": 37.8098752, "lon": -107.6850151}, {"type": "node", "id": 333721564, "lat": 37.8100072, "lon": -107.6852485}, {"type": "node", "id": 333721565, "lat": 37.81066, "lon": -107.6859951}, {"type": "node", "id": 333721566, "lat": 37.8108176, "lon": -107.6862554}, {"type": "node", "id": 333721567, "lat": 37.8110062, "lon": -107.6867763}, {"type": "node", "id": 333721572, "lat": 37.8110589, "lon": -107.6870933}, {"type": "node", "id": 333721573, "lat": 37.8111342, "lon": -107.6892924}, {"type": "node", "id": 333721574, "lat": 37.8111744, "lon": -107.6899421}, {"type": "node", "id": 333721575, "lat": 37.8112742, "lon": -107.690439}, {"type": "node", "id": 333721576, "lat": 37.8113775, "lon": -107.6907121}, {"type": "node", "id": 333721577, "lat": 37.8134459, "lon": -107.6940271}, {"type": "node", "id": 333721578, "lat": 37.8138382, "lon": -107.6946279}, {"type": "node", "id": 333721579, "lat": 37.8140308, "lon": -107.6948985}, {"type": "node", "id": 333721580, "lat": 37.8152446, "lon": -107.696094}, {"type": "node", "id": 333721581, "lat": 37.8154761, "lon": -107.696339}, {"type": "node", "id": 333721582, "lat": 37.8156645, "lon": -107.6965881}, {"type": "node", "id": 333721583, "lat": 37.8161048, "lon": -107.6972177, "tags": {"created_by": "Merkaartor 0.12"}}, {"type": "node", "id": 333721584, "lat": 37.8163824, "lon": -107.697545, "tags": {"created_by": "Merkaartor 0.12"}}, {"type": "node", "id": 333721585, "lat": 37.8165307, "lon": -107.697773, "tags": {"created_by": "Merkaartor 0.12"}}, {"type": "node", "id": 333721586, "lat": 37.8167537, "lon": -107.698252}, {"type": "node", "id": 333721587, "lat": 37.8168872, "lon": -107.6986304}, {"type": "node", "id": 333721588, "lat": 37.8089638, "lon": -107.6810896, "tags": {"created_by": "Merkaartor 0.12"}}, {"type": "node", "id": 333721589, "lat": 37.8094844, "lon": -107.6824468}, {"type": "node", "id": 333721590, "lat": 37.809685, "lon": -107.6844326}, {"type": "node", "id": 333721591, "lat": 37.8102252, "lon": -107.6855116}, {"type": "node", "id": 333721592, "lat": 37.8109059, "lon": -107.6864476}, {"type": "node", "id": 333721593, "lat": 37.811081, "lon": -107.6874659}, {"type": "node", "id": 333721594, "lat": 37.8111998, "lon": -107.6901375}, {"type": "node", "id": 333721595, "lat": 37.81163, "lon": -107.6911622}, {"type": "node", "id": 333721596, "lat": 37.8124733, "lon": -107.6925087}, {"type": "node", "id": 333721597, "lat": 37.8143126, "lon": -107.6952286}, {"type": "node", "id": 333721598, "lat": 37.8145521, "lon": -107.6954677}, {"type": "node", "id": 333721599, "lat": 37.8159144, "lon": -107.6969719}, {"type": "node", "id": 333721600, "lat": 37.8016806, "lon": -107.6770975}, {"type": "node", "id": 333721607, "lat": 37.8170626, "lon": -107.699222}, {"type": "node", "id": 333721608, "lat": 37.8172368, "lon": -107.6999835}, {"type": "node", "id": 333721609, "lat": 37.8173366, "lon": -107.7004082}, {"type": "node", "id": 333721610, "lat": 37.8173876, "lon": -107.700588}, {"type": "node", "id": 333722576, "lat": 37.8008044, "lon": -107.6762943}, {"type": "node", "id": 333722577, "lat": 37.8006494, "lon": -107.676123}, {"type": "node", "id": 333722578, "lat": 37.8004708, "lon": -107.6759239}, {"type": "node", "id": 333722579, "lat": 37.7999813, "lon": -107.6752343}, {"type": "node", "id": 333722580, "lat": 37.7997536, "lon": -107.6749895}, {"type": "node", "id": 333722581, "lat": 37.7993102, "lon": -107.6746804}, {"type": "node", "id": 333722582, "lat": 37.7989861, "lon": -107.6744955}, {"type": "node", "id": 333722583, "lat": 37.7984354, "lon": -107.6742527, "tags": {"created_by": "Merkaartor 0.12"}}, {"type": "node", "id": 333722584, "lat": 37.7978822, "lon": -107.6740584}, {"type": "node", "id": 333722585, "lat": 37.7976674, "lon": -107.6740024}, {"type": "node", "id": 333722586, "lat": 37.7969656, "lon": -107.6741656}, {"type": "node", "id": 333722589, "lat": 37.7967327, "lon": -107.674231}, {"type": "node", "id": 333722590, "lat": 37.7965386, "lon": -107.6742557}, {"type": "node", "id": 333722591, "lat": 37.7962499, "lon": -107.6742479}, {"type": "node", "id": 333722592, "lat": 37.7958114, "lon": -107.6741436}, {"type": "node", "id": 333722593, "lat": 37.7957005, "lon": -107.674091}, {"type": "node", "id": 333722594, "lat": 37.7952567, "lon": -107.6737859}, {"type": "node", "id": 333722595, "lat": 37.7947088, "lon": -107.6735648}, {"type": "node", "id": 333722596, "lat": 37.7945264, "lon": -107.6735192}, {"type": "node", "id": 333722597, "lat": 37.7940819, "lon": -107.6734647}, {"type": "node", "id": 333722598, "lat": 37.793676, "lon": -107.6734844}, {"type": "node", "id": 333722599, "lat": 37.7935034, "lon": -107.6734721, "tags": {"created_by": "Merkaartor 0.12"}}, {"type": "node", "id": 333722600, "lat": 37.7933847, "lon": -107.6734158, "tags": {"created_by": "Merkaartor 0.12"}}, {"type": "node", "id": 333722601, "lat": 37.7931597, "lon": -107.6732098}, {"type": "node", "id": 333722602, "lat": 37.7930401, "lon": -107.673125}, {"type": "node", "id": 333722603, "lat": 37.792352, "lon": -107.6729264}, {"type": "node", "id": 333722604, "lat": 37.7921871, "lon": -107.6728686, "tags": {"created_by": "Merkaartor 0.12"}}, {"type": "node", "id": 333722605, "lat": 37.7920065, "lon": -107.6727647}, {"type": "node", "id": 333722606, "lat": 37.7915376, "lon": -107.6725108}, {"type": "node", "id": 333722609, "lat": 37.7908028, "lon": -107.6723275}, {"type": "node", "id": 333722612, "lat": 37.7905926, "lon": -107.6722997}, {"type": "node", "id": 333722614, "lat": 37.7903134, "lon": -107.6723063}, {"type": "node", "id": 333722616, "lat": 37.7899992, "lon": -107.6724325}, {"type": "node", "id": 333722622, "lat": 37.7896442, "lon": -107.6726922}, {"type": "node", "id": 333722624, "lat": 37.7894927, "lon": -107.6728609}, {"type": "node", "id": 333722626, "lat": 37.7996066, "lon": -107.6748684}, {"type": "node", "id": 333722629, "lat": 37.7987547, "lon": -107.6743775}, {"type": "node", "id": 333722632, "lat": 37.7973696, "lon": -107.6740044}, {"type": "node", "id": 333722635, "lat": 37.797267, "lon": -107.6740337}, {"type": "node", "id": 333722638, "lat": 37.7959107, "lon": -107.6741819}, {"type": "node", "id": 333722639, "lat": 37.7951111, "lon": -107.6737182}, {"type": "node", "id": 333722640, "lat": 37.7942951, "lon": -107.6734744}, {"type": "node", "id": 333722641, "lat": 37.7917881, "lon": -107.6726313}, {"type": "node", "id": 333722642, "lat": 37.7911905, "lon": -107.6723997}, {"type": "node", "id": 333722644, "lat": 37.7901622, "lon": -107.6723557}, {"type": "node", "id": 333722650, "lat": 37.7898489, "lon": -107.6725287}, {"type": "node", "id": 333722651, "lat": 37.7893767, "lon": -107.6729816}, {"type": "node", "id": 333722652, "lat": 37.7891688, "lon": -107.673149}, {"type": "node", "id": 333722653, "lat": 37.7890812, "lon": -107.6731744}, {"type": "node", "id": 1356606876, "lat": 37.8044627, "lon": -107.6720659}, {"type": "node", "id": 1356606879, "lat": 37.8046698, "lon": -107.6721055}, {"type": "node", "id": 1356606891, "lat": 37.8054057, "lon": -107.6713677}, {"type": "node", "id": 1356606892, "lat": 37.8055113, "lon": -107.6712321}, {"type": "node", "id": 1618481603, "lat": 37.8052254, "lon": -107.67031}, {"type": "node", "id": 1826005504, "lat": 37.8111838, "lon": -107.6687122}, {"type": "node", "id": 1826005506, "lat": 37.8125684, "lon": -107.6687888}, {"type": "node", "id": 1826005507, "lat": 37.8043293, "lon": -107.6677159}, {"type": "node", "id": 1826005508, "lat": 37.8059701, "lon": -107.6658323}, {"type": "node", "id": 2042183213, "lat": 37.8068032, "lon": -107.6695009}, {"type": "node", "id": 2042183214, "lat": 37.8066776, "lon": -107.6669376}, {"type": "node", "id": 2042183217, "lat": 37.810742, "lon": -107.6672459}, {"type": "node", "id": 2042183218, "lat": 37.8158726, "lon": -107.6625108}, {"type": "node", "id": 2042183222, "lat": 37.816438, "lon": -107.6593052}, {"type": "node", "id": 2042183223, "lat": 37.8124081, "lon": -107.6657019}, {"type": "node", "id": 2042183231, "lat": 37.8137436, "lon": -107.6590943}, {"type": "node", "id": 2042183239, "lat": 37.8174389, "lon": -107.6599748}, {"type": "node", "id": 2042183241, "lat": 37.8100476, "lon": -107.66386}, {"type": "node", "id": 2042183256, "lat": 37.8088711, "lon": -107.666274}, {"type": "node", "id": 2042183257, "lat": 37.8127247, "lon": -107.6640414}, {"type": "node", "id": 2042183261, "lat": 37.8059976, "lon": -107.6702298}, {"type": "node", "id": 2042183267, "lat": 37.8135789, "lon": -107.6632935}, {"type": "node", "id": 2042183268, "lat": 37.8145866, "lon": -107.6650151}, {"type": "node", "id": 2042183269, "lat": 37.8061325, "lon": -107.6661141}, {"type": "node", "id": 2042183272, "lat": 37.8112269, "lon": -107.6680929}, {"type": "node", "id": 2042183276, "lat": 37.8140866, "lon": -107.6641606}, {"type": "node", "id": 2042183279, "lat": 37.8058594, "lon": -107.6657771}, {"type": "node", "id": 2042183281, "lat": 37.8140963, "lon": -107.6574137}, {"type": "node", "id": 2042183289, "lat": 37.8155637, "lon": -107.6600956}, {"type": "node", "id": 2042183301, "lat": 37.812057, "lon": -107.6606225}, {"type": "node", "id": 2042183303, "lat": 37.8113819, "lon": -107.6639534}, {"type": "node", "id": 2042183315, "lat": 37.8095235, "lon": -107.662974}, {"type": "node", "id": 2042183317, "lat": 37.8110656, "lon": -107.6655804}, {"type": "node", "id": 2042183325, "lat": 37.8153227, "lon": -107.6640733}, {"type": "node", "id": 2042183330, "lat": 37.8173011, "lon": -107.6599533}, {"type": "node", "id": 2042183331, "lat": 37.8176414, "lon": -107.661971}, {"type": "node", "id": 2042183334, "lat": 37.8129017, "lon": -107.6598582}, {"type": "node", "id": 2042183336, "lat": 37.806517, "lon": -107.6711114}, {"type": "node", "id": 2042183339, "lat": 37.8149535, "lon": -107.6633672}, {"type": "node", "id": 2042183342, "lat": 37.8105546, "lon": -107.6647176}, {"type": "node", "id": 2042183346, "lat": 37.815651, "lon": -107.6621783}, {"type": "node", "id": 2042183350, "lat": 37.812215, "lon": -107.6631766}, {"type": "node", "id": 2042183353, "lat": 37.8102147, "lon": -107.6663719}, {"type": "node", "id": 2042183368, "lat": 37.8086895, "lon": -107.6637536}, {"type": "node", "id": 2042183371, "lat": 37.8132272, "lon": -107.6582294}, {"type": "node", "id": 2042183372, "lat": 37.8144419, "lon": -107.6625131}, {"type": "node", "id": 2042183373, "lat": 37.8073006, "lon": -107.6703721}, {"type": "node", "id": 2042183378, "lat": 37.8081853, "lon": -107.6695936}, {"type": "node", "id": 2042183381, "lat": 37.8150744, "lon": -107.6591881}, {"type": "node", "id": 2042183387, "lat": 37.8085147, "lon": -107.667928}, {"type": "node", "id": 2042183391, "lat": 37.8159038, "lon": -107.6583436}, {"type": "node", "id": 2042183392, "lat": 37.8080224, "lon": -107.6670679}, {"type": "node", "id": 2042183396, "lat": 37.8125616, "lon": -107.6614966}, {"type": "node", "id": 2042183398, "lat": 37.807687, "lon": -107.668707}, {"type": "node", "id": 2042183401, "lat": 37.8115728, "lon": -107.6664652}, {"type": "node", "id": 2042183404, "lat": 37.8075056, "lon": -107.6661701}, {"type": "node", "id": 2042183405, "lat": 37.8130808, "lon": -107.6624065}, {"type": "node", "id": 2042183406, "lat": 37.8091882, "lon": -107.6646159}, {"type": "node", "id": 2042183407, "lat": 37.8120737, "lon": -107.6673323}, {"type": "node", "id": 2042183408, "lat": 37.8123874, "lon": -107.6590069}, {"type": "node", "id": 2042183411, "lat": 37.8118851, "lon": -107.6648295}, {"type": "node", "id": 2042183415, "lat": 37.8097088, "lon": -107.6655127}, {"type": "node", "id": 2042183417, "lat": 37.8083543, "lon": -107.6654051}, {"type": "node", "id": 2042183425, "lat": 37.8154204, "lon": -107.6575289}, {"type": "node", "id": 2042183426, "lat": 37.8154529, "lon": -107.6602328}, {"type": "node", "id": 2042183427, "lat": 37.8115613, "lon": -107.6597801}, {"type": "node", "id": 2042183436, "lat": 37.8071832, "lon": -107.6678329}, {"type": "node", "id": 2042183439, "lat": 37.8132435, "lon": -107.6649289}, {"type": "node", "id": 2042183444, "lat": 37.8093798, "lon": -107.6671483}, {"type": "node", "id": 2042183451, "lat": 37.814799, "lon": -107.6608049}, {"type": "node", "id": 2042183454, "lat": 37.8078602, "lon": -107.6645587}, {"type": "node", "id": 2042183456, "lat": 37.814282, "lon": -107.6599616}, {"type": "node", "id": 2042183459, "lat": 37.8059188, "lon": -107.6700764}, {"type": "node", "id": 2048180107, "lat": 37.8155771, "lon": -107.6964678}, {"type": "node", "id": 2048180112, "lat": 37.8028034, "lon": -107.6776951}, {"type": "node", "id": 2048180115, "lat": 37.8034254, "lon": -107.6741305}, {"type": "node", "id": 2048180120, "lat": 37.8079107, "lon": -107.6768862}, {"type": "node", "id": 2048180121, "lat": 37.810957, "lon": -107.6866004}, {"type": "node", "id": 2048180129, "lat": 37.8040161, "lon": -107.6715213}, {"type": "node", "id": 2048180135, "lat": 37.8164488, "lon": -107.6976438}, {"type": "node", "id": 2048180137, "lat": 37.8058633, "lon": -107.6801468}, {"type": "node", "id": 2048180138, "lat": 37.8095856, "lon": -107.6839966}, {"type": "node", "id": 2048180140, "lat": 37.8057278, "lon": -107.6801277}, {"type": "node", "id": 2048180142, "lat": 37.8110362, "lon": -107.686942}, {"type": "node", "id": 2048180143, "lat": 37.8096201, "lon": -107.68417}, {"type": "node", "id": 2048180144, "lat": 37.8114386, "lon": -107.6908402}, {"type": "node", "id": 2048180154, "lat": 37.8144247, "lon": -107.695344}, {"type": "node", "id": 2048180156, "lat": 37.8169523, "lon": -107.6988363}, {"type": "node", "id": 2048180160, "lat": 37.8170117, "lon": -107.6990277}, {"type": "node", "id": 2048180170, "lat": 37.805574, "lon": -107.6781048}, {"type": "node", "id": 2048180172, "lat": 37.8094992, "lon": -107.6831405}, {"type": "node", "id": 2048180176, "lat": 37.8026863, "lon": -107.6776338}, {"type": "node", "id": 2048180177, "lat": 37.8070614, "lon": -107.668608}, {"type": "node", "id": 2048180181, "lat": 37.8094463, "lon": -107.6821371}, {"type": "node", "id": 2048180182, "lat": 37.8048383, "lon": -107.6709067}, {"type": "node", "id": 2048180184, "lat": 37.8047645, "lon": -107.6762456}, {"type": "node", "id": 2048180185, "lat": 37.80616, "lon": -107.6798865}, {"type": "node", "id": 2048180188, "lat": 37.8110712, "lon": -107.6872819}, {"type": "node", "id": 2048180190, "lat": 37.8139257, "lon": -107.69476}, {"type": "node", "id": 2048180192, "lat": 37.8050364, "lon": -107.6794002}, {"type": "node", "id": 2048180196, "lat": 37.8045539, "lon": -107.6789857}, {"type": "node", "id": 2048180198, "lat": 37.8039271, "lon": -107.6786135}, {"type": "node", "id": 2048180203, "lat": 37.8061871, "lon": -107.6795561}, {"type": "node", "id": 2048180204, "lat": 37.8060873, "lon": -107.6800172}, {"type": "node", "id": 2048180208, "lat": 37.8162124, "lon": -107.6973446}, {"type": "node", "id": 2048180219, "lat": 37.8112327, "lon": -107.6902865}, {"type": "node", "id": 2048180223, "lat": 37.8034713, "lon": -107.6782695}, {"type": "node", "id": 2048180224, "lat": 37.8094659, "lon": -107.6822689}, {"type": "node", "id": 2048180225, "lat": 37.8048744, "lon": -107.6764924}, {"type": "node", "id": 2048180227, "lat": 37.8093798, "lon": -107.6819086}, {"type": "node", "id": 2048180236, "lat": 37.8099308, "lon": -107.6851234}, {"type": "node", "id": 2048180239, "lat": 37.8030534, "lon": -107.6778708}, {"type": "node", "id": 2048180249, "lat": 37.8166958, "lon": -107.6981094}, {"type": "node", "id": 2048180251, "lat": 37.8141453, "lon": -107.6950357}, {"type": "node", "id": 2048180264, "lat": 37.8043401, "lon": -107.6753892}, {"type": "node", "id": 2048180266, "lat": 37.8115204, "lon": -107.6909946}, {"type": "node", "id": 2048180273, "lat": 37.8046067, "lon": -107.6721337}, {"type": "node", "id": 2048180283, "lat": 37.8166197, "lon": -107.6979355}, {"type": "node", "id": 2048180287, "lat": 37.8036804, "lon": -107.674104}, {"type": "node", "id": 2048180289, "lat": 37.8100986, "lon": -107.6853621}, {"type": "node", "id": 2048180295, "lat": 37.8119154, "lon": -107.691624}, {"type": "node", "id": 2048180302, "lat": 37.8035419, "lon": -107.673125}, {"type": "node", "id": 2048180306, "lat": 37.811143, "lon": -107.6895057}, {"type": "node", "id": 2048180307, "lat": 37.8059056, "lon": -107.6788266}, {"type": "node", "id": 2048180323, "lat": 37.8039354, "lon": -107.6746682}, {"type": "node", "id": 2048180327, "lat": 37.8075504, "lon": -107.6758767}, {"type": "node", "id": 2048180333, "lat": 37.8022099, "lon": -107.6774564}, {"type": "node", "id": 2048180346, "lat": 37.8060735, "lon": -107.6792162}, {"type": "node", "id": 2048180360, "lat": 37.8088203, "lon": -107.6807648}, {"type": "node", "id": 2048180371, "lat": 37.8059866, "lon": -107.6801103}, {"type": "node", "id": 2048180375, "lat": 37.8035431, "lon": -107.6732762}, {"type": "node", "id": 2048180379, "lat": 37.8105757, "lon": -107.6859062}, {"type": "node", "id": 2048180381, "lat": 37.8095123, "lon": -107.6833766}, {"type": "node", "id": 2048180387, "lat": 37.8035481, "lon": -107.6743633}, {"type": "node", "id": 2048180389, "lat": 37.8110992, "lon": -107.6880789}, {"type": "node", "id": 2048180393, "lat": 37.8097662, "lon": -107.6847342}, {"type": "node", "id": 2048180418, "lat": 37.8054315, "lon": -107.6798367}, {"type": "node", "id": 2048180424, "lat": 37.8035497, "lon": -107.6728283}, {"type": "node", "id": 2048180434, "lat": 37.8111615, "lon": -107.6897738}, {"type": "node", "id": 2048180440, "lat": 37.8045432, "lon": -107.6721145}, {"type": "node", "id": 2048180442, "lat": 37.8055974, "lon": -107.6800399}, {"type": "node", "id": 2048180458, "lat": 37.8039403, "lon": -107.6687794}, {"type": "node", "id": 2048180460, "lat": 37.8036069, "lon": -107.6744215}, {"type": "node", "id": 2048180462, "lat": 37.8157934, "lon": -107.6967958}, {"type": "node", "id": 2048180471, "lat": 37.8061904, "lon": -107.6797326}, {"type": "node", "id": 2048180482, "lat": 37.8113205, "lon": -107.6905812}, {"type": "node", "id": 2048180486, "lat": 37.8092874, "lon": -107.681674}, {"type": "node", "id": 2048180488, "lat": 37.8168145, "lon": -107.6984207}, {"type": "node", "id": 2048180492, "lat": 37.8107562, "lon": -107.6861509}, {"type": "node", "id": 2048180493, "lat": 37.803801, "lon": -107.6718765}, {"type": "node", "id": 2048180495, "lat": 37.8087142, "lon": -107.6804232}, {"type": "node", "id": 2048180496, "lat": 37.8058207, "lon": -107.6718231}, {"type": "node", "id": 2048198595, "lat": 37.8269635, "lon": -107.6688504}, {"type": "node", "id": 2048198671, "lat": 37.8274461, "lon": -107.6691989}, {"type": "node", "id": 2048198720, "lat": 37.8248446, "lon": -107.6667517}, {"type": "node", "id": 2048198773, "lat": 37.8272618, "lon": -107.6691164}, {"type": "node", "id": 2048198776, "lat": 37.8285418, "lon": -107.6697897}, {"type": "node", "id": 2048198779, "lat": 37.8283295, "lon": -107.6694667}, {"type": "node", "id": 2048198851, "lat": 37.8291456, "lon": -107.6704814}, {"type": "node", "id": 2048198897, "lat": 37.8281535, "lon": -107.6692921}, {"type": "node", "id": 2048198901, "lat": 37.8253714, "lon": -107.6671991}, {"type": "node", "id": 2048198927, "lat": 37.8275355, "lon": -107.6692169}, {"type": "node", "id": 2048198954, "lat": 37.828939, "lon": -107.6703409}, {"type": "node", "id": 2048199022, "lat": 37.8265641, "lon": -107.6682894}, {"type": "node", "id": 2048199108, "lat": 37.8259016, "lon": -107.6675435}, {"type": "node", "id": 2048199117, "lat": 37.8288292, "lon": -107.6702466}, {"type": "node", "id": 2048199120, "lat": 37.8264007, "lon": -107.6680276}, {"type": "node", "id": 2048199284, "lat": 37.8268026, "lon": -107.6686599}, {"type": "node", "id": 2048199403, "lat": 37.8252023, "lon": -107.6670674}, {"type": "node", "id": 2048199419, "lat": 37.8261813, "lon": -107.6677855}, {"type": "node", "id": 2050001822, "lat": 37.7897651, "lon": -107.6725906}, {"type": "node", "id": 2050001824, "lat": 37.7935758, "lon": -107.6734855}, {"type": "node", "id": 2050001829, "lat": 37.8009912, "lon": -107.6764656}, {"type": "node", "id": 2050001834, "lat": 37.7980633, "lon": -107.6741154}, {"type": "node", "id": 2050001838, "lat": 37.7968271, "lon": -107.6742124}, {"type": "node", "id": 2050001841, "lat": 37.7953894, "lon": -107.6738745}, {"type": "node", "id": 2050001842, "lat": 37.7913965, "lon": -107.6724549}, {"type": "node", "id": 2050001845, "lat": 37.7892679, "lon": -107.6730845}, {"type": "node", "id": 2050001854, "lat": 37.7975603, "lon": -107.6739981}, {"type": "node", "id": 2050001861, "lat": 37.7934492, "lon": -107.6734529}, {"type": "node", "id": 2050001863, "lat": 37.7904451, "lon": -107.6722931}, {"type": "node", "id": 2050001864, "lat": 37.7974756, "lon": -107.6739958}, {"type": "node", "id": 2050001881, "lat": 37.7961438, "lon": -107.6742388}, {"type": "node", "id": 2050001882, "lat": 37.7977685, "lon": -107.674023}, {"type": "node", "id": 2050001885, "lat": 37.7998562, "lon": -107.675081}, {"type": "node", "id": 2050001886, "lat": 37.8003182, "lon": -107.6757166}, {"type": "node", "id": 2050001888, "lat": 37.793285, "lon": -107.673329}, {"type": "node", "id": 2050001889, "lat": 37.7960337, "lon": -107.6742196}, {"type": "node", "id": 2050001899, "lat": 37.7964115, "lon": -107.6742534}, {"type": "node", "id": 2050001902, "lat": 37.7952391, "lon": -107.669476}, {"type": "node", "id": 2050001906, "lat": 37.7919077, "lon": -107.672705}, {"type": "node", "id": 2050001910, "lat": 37.7941987, "lon": -107.6734663}, {"type": "node", "id": 2050001911, "lat": 37.7950005, "lon": -107.67367}, {"type": "node", "id": 2050001923, "lat": 37.795608, "lon": -107.6740261}, {"type": "node", "id": 2050001926, "lat": 37.7893216, "lon": -107.6730412}, {"type": "node", "id": 2050001934, "lat": 37.7944176, "lon": -107.6734931}, {"type": "node", "id": 2050001936, "lat": 37.7927976, "lon": -107.6730429}, {"type": "node", "id": 2050001948, "lat": 37.792927, "lon": -107.6730751}, {"type": "node", "id": 2050001949, "lat": 37.8000924, "lon": -107.6753958}, {"type": "node", "id": 2050001953, "lat": 37.7925576, "lon": -107.6729749}, {"type": "node", "id": 2050001955, "lat": 37.7991463, "lon": -107.6745831}, {"type": "node", "id": 2050001957, "lat": 37.796621, "lon": -107.6742483}, {"type": "node", "id": 2050001958, "lat": 37.7958377, "lon": -107.6695161}, {"type": "node", "id": 2050001959, "lat": 37.8015748, "lon": -107.6770006}, {"type": "node", "id": 2084019365, "lat": 37.8111337, "lon": -107.6587563}, {"type": "node", "id": 2084019366, "lat": 37.8113838, "lon": -107.6578586}, {"type": "node", "id": 2084019367, "lat": 37.8114937, "lon": -107.6572542}, {"type": "node", "id": 2084019368, "lat": 37.8114968, "lon": -107.6570223}, {"type": "node", "id": 2084070404, "lat": 37.8340003, "lon": -107.6733864}, {"type": "node", "id": 2899369376, "lat": 37.8182178, "lon": -107.6583012}, {"type": "node", "id": 2899369377, "lat": 37.818141, "lon": -107.6583156}, {"type": "node", "id": 2899369378, "lat": 37.8180888, "lon": -107.658396}, {"type": "node", "id": 2899369379, "lat": 37.8183818, "lon": -107.658444}, {"type": "node", "id": 2899369380, "lat": 37.8185686, "lon": -107.6588414}, {"type": "node", "id": 2899369381, "lat": 37.8182965, "lon": -107.6583516}, {"type": "node", "id": 3042563270, "lat": 37.8101077, "lon": -107.6617323}, {"type": "node", "id": 3042563877, "lat": 37.8088158, "lon": -107.6617505}, {"type": "node", "id": 3042563878, "lat": 37.8077726, "lon": -107.662269}, {"type": "node", "id": 3042563879, "lat": 37.8075602, "lon": -107.662197}, {"type": "node", "id": 3042563880, "lat": 37.8071998, "lon": -107.6623939}, {"type": "node", "id": 3042563881, "lat": 37.8068205, "lon": -107.662682}, {"type": "node", "id": 3042563882, "lat": 37.8065132, "lon": -107.6630565}, {"type": "node", "id": 3042563883, "lat": 37.8061453, "lon": -107.6636806}, {"type": "node", "id": 3042563884, "lat": 37.8057052, "lon": -107.6640551}, {"type": "node", "id": 3042563885, "lat": 37.8051855, "lon": -107.6645929}, {"type": "node", "id": 3042563886, "lat": 37.8047379, "lon": -107.6649194}, {"type": "node", "id": 3042563887, "lat": 37.8046317, "lon": -107.6650586}, {"type": "node", "id": 3042563888, "lat": 37.8045748, "lon": -107.6654859}, {"type": "node", "id": 3067755389, "lat": 37.8080155, "lon": -107.6626188, "tags": {"railway": "level_crossing"}}, {"type": "node", "id": 3067755413, "lat": 37.8101183, "lon": -107.6617941, "tags": {"railway": "level_crossing"}}, {"type": "node", "id": 3975607028, "lat": 37.7906613, "lon": -107.669266}, {"type": "node", "id": 3975607029, "lat": 37.7907752, "lon": -107.6692407}, {"type": "node", "id": 4559503017, "lat": 37.815694, "lon": -107.6966357}, {"type": "node", "id": 4626926801, "lat": 37.8078945, "lon": -107.6624409, "tags": {"railway": "level_crossing"}}, {"type": "node", "id": 4676573324, "lat": 37.8100986, "lon": -107.6618118, "tags": {"railway": "level_crossing"}}, {"type": "node", "id": 4676573325, "lat": 37.8105948, "lon": -107.6626786, "tags": {"railway": "level_crossing"}}, {"type": "node", "id": 4676573326, "lat": 37.8106146, "lon": -107.6626606, "tags": {"railway": "level_crossing"}}, {"type": "node", "id": 4973035049, "lat": 37.8115517, "lon": -107.6642517}, {"type": "node", "id": 4973035050, "lat": 37.8117147, "lon": -107.6645357}, {"type": "node", "id": 4973035051, "lat": 37.8066206, "lon": -107.6691857}, {"type": "node", "id": 5224262766, "lat": 37.8155059, "lon": -107.6643283}, {"type": "node", "id": 5224262792, "lat": 37.8155374, "lon": -107.664354}, {"type": "node", "id": 5224262994, "lat": 37.8121477, "lon": -107.6679428}, {"type": "node", "id": 5224262995, "lat": 37.8121938, "lon": -107.6678509}, {"type": "node", "id": 5224262996, "lat": 37.8122123, "lon": -107.6676652}, {"type": "node", "id": 5224262997, "lat": 37.8121933, "lon": -107.6675659}, {"type": "node", "id": 5224262998, "lat": 37.8113676, "lon": -107.6685534}, {"type": "node", "id": 5224262999, "lat": 37.8112662, "lon": -107.6686288}, {"type": "node", "id": 5224263000, "lat": 37.811779, "lon": -107.6683894}, {"type": "node", "id": 5224263001, "lat": 37.8118728, "lon": -107.6683062}, {"type": "node", "id": 5224263002, "lat": 37.8068915, "lon": -107.6717087}, {"type": "node", "id": 5224263003, "lat": 37.8075008, "lon": -107.6727561}, {"type": "node", "id": 5224263004, "lat": 37.8076364, "lon": -107.6730028}, {"type": "node", "id": 5224263005, "lat": 37.8077551, "lon": -107.6732281}, {"type": "node", "id": 5224263006, "lat": 37.8078568, "lon": -107.673432}, {"type": "node", "id": 5224263007, "lat": 37.8079076, "lon": -107.6736036}, {"type": "node", "id": 5224263008, "lat": 37.8080093, "lon": -107.6740972}, {"type": "node", "id": 5224263009, "lat": 37.8081323, "lon": -107.6747141}, {"type": "node", "id": 5224263010, "lat": 37.8082213, "lon": -107.6750306}, {"type": "node", "id": 5224263011, "lat": 37.8083484, "lon": -107.6754919}, {"type": "node", "id": 5224263012, "lat": 37.8083993, "lon": -107.6757494}, {"type": "node", "id": 5224263013, "lat": 37.8084416, "lon": -107.6759425}, {"type": "node", "id": 5224263014, "lat": 37.8083908, "lon": -107.676082}, {"type": "node", "id": 5224263015, "lat": 37.8082806, "lon": -107.6761678}, {"type": "node", "id": 5224263016, "lat": 37.8081619, "lon": -107.6761786}, {"type": "node", "id": 5224263017, "lat": 37.8080602, "lon": -107.6760713}, {"type": "node", "id": 5224263018, "lat": 37.8079839, "lon": -107.6758889}, {"type": "node", "id": 5224263019, "lat": 37.8078822, "lon": -107.6755885}, {"type": "node", "id": 5224263020, "lat": 37.8078218, "lon": -107.6753404}, {"type": "node", "id": 5224263121, "lat": 37.807789, "lon": -107.6751164}, {"type": "node", "id": 5224263122, "lat": 37.8078313, "lon": -107.6749555}, {"type": "node", "id": 5224263123, "lat": 37.8079246, "lon": -107.6749018}, {"type": "node", "id": 5224263124, "lat": 37.8080517, "lon": -107.6747838}, {"type": "node", "id": 5224263125, "lat": 37.8077911, "lon": -107.675048}, {"type": "node", "id": 5224263126, "lat": 37.8078038, "lon": -107.6749923}, {"type": "node", "id": 5224263127, "lat": 37.8078864, "lon": -107.6735138}, {"type": "node", "id": 5224263128, "lat": 37.8067174, "lon": -107.6714495}, {"type": "node", "id": 5224263129, "lat": 37.8066468, "lon": -107.6713797}, {"type": "node", "id": 5224263130, "lat": 37.8065745, "lon": -107.6712415}, {"type": "node", "id": 5224263131, "lat": 37.80744, "lon": -107.6660379}, {"type": "node", "id": 5224263132, "lat": 37.8074157, "lon": -107.6659811}, {"type": "node", "id": 5224263133, "lat": 37.8073856, "lon": -107.665862}, {"type": "node", "id": 5224263134, "lat": 37.8073851, "lon": -107.6657514}, {"type": "node", "id": 5224263135, "lat": 37.8074168, "lon": -107.6656441}, {"type": "node", "id": 5224263136, "lat": 37.8074687, "lon": -107.6655597}, {"type": "node", "id": 5224263137, "lat": 37.8076913, "lon": -107.6642353}, {"type": "node", "id": 5224263138, "lat": 37.8076801, "lon": -107.6641773}, {"type": "node", "id": 5224263139, "lat": 37.8076965, "lon": -107.6640536}, {"type": "node", "id": 5224263140, "lat": 37.8077304, "lon": -107.6639979}, {"type": "node", "id": 5224263141, "lat": 37.8077739, "lon": -107.6639406}, {"type": "node", "id": 5224263142, "lat": 37.8114578, "lon": -107.6575537}, {"type": "node", "id": 5224263143, "lat": 37.8114821, "lon": -107.657412}, {"type": "node", "id": 5224263144, "lat": 37.8111202, "lon": -107.6589266}, {"type": "node", "id": 5224263145, "lat": 37.8111185, "lon": -107.6588626}, {"type": "node", "id": 5224263146, "lat": 37.8111224, "lon": -107.6588199}, {"type": "node", "id": 5224263147, "lat": 37.8112895, "lon": -107.6620257}, {"type": "node", "id": 5224263148, "lat": 37.8113501, "lon": -107.6619908}, {"type": "node", "id": 5224263149, "lat": 37.811454, "lon": -107.6620009}, {"type": "node", "id": 5224263150, "lat": 37.811618, "lon": -107.6621666}, {"type": "node", "id": 5224263151, "lat": 37.8115634, "lon": -107.6620881}, {"type": "node", "id": 5224263152, "lat": 37.8115319, "lon": -107.6620556}, {"type": "node", "id": 5224263153, "lat": 37.8113177, "lon": -107.6620056}, {"type": "node", "id": 5224263190, "lat": 37.8155751, "lon": -107.6621653}, {"type": "node", "id": 5224263191, "lat": 37.8156788, "lon": -107.6621979}, {"type": "node", "id": 5224263192, "lat": 37.8155497, "lon": -107.6621687}, {"type": "node", "id": 5224263193, "lat": 37.8172321, "lon": -107.6619212}, {"type": "node", "id": 5224263194, "lat": 37.8172697, "lon": -107.6619031}, {"type": "node", "id": 5224263195, "lat": 37.8173741, "lon": -107.6618931}, {"type": "node", "id": 5224263196, "lat": 37.8185511, "lon": -107.6622552}, {"type": "node", "id": 5224263197, "lat": 37.8183622, "lon": -107.6555061}, {"type": "node", "id": 5224263198, "lat": 37.8184053, "lon": -107.6554138}, {"type": "node", "id": 5224263199, "lat": 37.8184722, "lon": -107.6552632}, {"type": "node", "id": 5224263200, "lat": 37.8184946, "lon": -107.6550773}, {"type": "node", "id": 5224263201, "lat": 37.8184847, "lon": -107.6549571}, {"type": "node", "id": 5224263202, "lat": 37.8184268, "lon": -107.6547198}, {"type": "node", "id": 5224263203, "lat": 37.818392, "lon": -107.6546287}, {"type": "node", "id": 5224263204, "lat": 37.8179724, "lon": -107.6541256}, {"type": "node", "id": 5224263205, "lat": 37.8179365, "lon": -107.6540746}, {"type": "node", "id": 5224263206, "lat": 37.8178497, "lon": -107.6539318}, {"type": "node", "id": 5224263207, "lat": 37.817801, "lon": -107.653829}, {"type": "node", "id": 5224263208, "lat": 37.8177734, "lon": -107.6537552}, {"type": "node", "id": 5224263209, "lat": 37.8177062, "lon": -107.6535274}, {"type": "node", "id": 5224263210, "lat": 37.8176609, "lon": -107.6532332}, {"type": "node", "id": 5224263211, "lat": 37.8176609, "lon": -107.6530863}, {"type": "node", "id": 5224263212, "lat": 37.8176705, "lon": -107.6529946}, {"type": "node", "id": 5224263213, "lat": 37.8177167, "lon": -107.6526745}, {"type": "node", "id": 5224263214, "lat": 37.8177911, "lon": -107.6521863}, {"type": "node", "id": 5224263215, "lat": 37.8178438, "lon": -107.651972}, {"type": "node", "id": 5224263216, "lat": 37.8179079, "lon": -107.6516117}, {"type": "node", "id": 5224263217, "lat": 37.817912, "lon": -107.6515245}, {"type": "node", "id": 5224263218, "lat": 37.8182922, "lon": -107.6544517}, {"type": "node", "id": 5224263219, "lat": 37.8182204, "lon": -107.6543651}, {"type": "node", "id": 5224263220, "lat": 37.8181327, "lon": -107.6542908}, {"type": "node", "id": 5224263221, "lat": 37.8182571, "lon": -107.6544074}, {"type": "node", "id": 5224263222, "lat": 37.818121, "lon": -107.6580736}, {"type": "node", "id": 5224263223, "lat": 37.8181417, "lon": -107.6578536}, {"type": "node", "id": 5224263224, "lat": 37.8183343, "lon": -107.6583816}, {"type": "node", "id": 5224263225, "lat": 37.8182709, "lon": -107.6580112}, {"type": "node", "id": 5224263226, "lat": 37.8182246, "lon": -107.6577628}, {"type": "node", "id": 5224263227, "lat": 37.8097495, "lon": -107.662071}, {"type": "node", "id": 5224263228, "lat": 37.8099113, "lon": -107.6619307}, {"type": "node", "id": 5224263229, "lat": 37.808905, "lon": -107.6628827}, {"type": "node", "id": 5224263230, "lat": 37.8090976, "lon": -107.662703}, {"type": "node", "id": 5224263281, "lat": 37.8059306, "lon": -107.6657926}, {"type": "node", "id": 5224263282, "lat": 37.8066789, "lon": -107.6714267}, {"type": "node", "id": 5224263283, "lat": 37.8068267, "lon": -107.6714464}, {"type": "node", "id": 5224263284, "lat": 37.8071546, "lon": -107.6711466}, {"type": "node", "id": 5224263285, "lat": 37.8074677, "lon": -107.6707014}, {"type": "node", "id": 5224263286, "lat": 37.8074523, "lon": -107.6706437}, {"type": "node", "id": 5224263287, "lat": 37.8074364, "lon": -107.670849}, {"type": "node", "id": 5224263288, "lat": 37.80746, "lon": -107.6708034}, {"type": "node", "id": 5226028614, "lat": 37.8210256, "lon": -107.6421629}, {"type": "node", "id": 5226032030, "lat": 37.8229904, "lon": -107.6394328}, {"type": "node", "id": 6191492208, "lat": 37.8303566, "lon": -107.6706896}, {"type": "node", "id": 7918999647, "lat": 37.8027839, "lon": -107.6776847}, {"type": "node", "id": 7919003634, "lat": 37.8225227, "lon": -107.6646364, "tags": {"elevation": "2904", "information": "sign", "name": "Pavement Ends", "tourism": "information"}}, {"type": "node", "id": 7919017538, "lat": 37.8053491, "lon": -107.6714237}, {"type": "node", "id": 9234256700, "lat": 37.8068364, "lon": -107.6715952}, {"type": "node", "id": 9234330036, "lat": 37.8161316, "lon": -107.6602568}, {"type": "way", "id": 29985489, "nodes": [178056227, 333722653, 333722652, 2050001845, 2050001926, 333722651, 333722624, 333722622, 2050001822, 333722650, 333722616, 333722644, 333722614, 2050001863, 333722612, 333722609, 333722642, 2050001842, 333722606, 333722641, 2050001906, 333722605, 333722604, 333722603, 2050001953, 2050001936, 2050001948, 333722602, 333722601, 2050001888, 333722600, 2050001861, 333722599, 2050001824, 333722598, 333722597, 2050001910, 333722640, 2050001934, 333722596, 333722595, 2050001911, 333722639, 333722594, 2050001841, 2050001923, 333722593, 333722592, 333722638, 2050001889, 2050001881, 333722591, 2050001899, 333722590, 2050001957, 333722589, 2050001838, 333722586, 333722635, 333722632, 2050001864, 2050001854, 333722585, 2050001882, 333722584, 2050001834, 333722583, 333722629, 333722582, 2050001955, 333722581, 333722626, 333722580, 2050001885, 333722579, 2050001949, 2050001886, 333722578, 333722577, 333722576, 2050001829, 2050001959, 333721600, 333721554, 333721553, 333721552, 2048180333, 333721551, 2048180176, 7918999647, 2048180112, 333721550, 2048180239, 331107679, 2048180223, 331107678, 331107677, 2048180198, 331107676, 2048180196, 331107675, 2048180192, 331107674, 2048180418, 331107673, 2048180442, 331107689, 2048180140, 331107672, 2048180137, 331107671, 2048180371, 331107670, 2048180204, 331107688, 2048180185, 331107669, 2048180471, 331107668, 2048180203, 331107667, 331107666, 2048180346, 2048180307, 2048180170, 331107665, 2048180225, 2048180184, 2048180264, 331107625, 2048180323, 331107624, 331107623, 2048180287, 330098621, 330098622, 330098623, 330098625], "tags": {"FIXME": "Check lanes and medians.", "NHS": "yes", "hgv": "designated", "hgv:national_network": "yes", "highway": "trunk", "lanes": "2", "nat_name": "United States Route 550", "ref": "US 550", "source:hgv:national_network": "CDOT \"Highway Data Explorer\"", "surface": "asphalt"}}, {"type": "way", "id": 29985494, "nodes": [330098669, 330098670, 2048180496, 331050841, 2048180327, 331050882, 331050884, 2048180120, 331050887, 331051212, 331050890, 331050892, 2048180495, 333721555, 2048180360, 333721556, 333721588, 333721557, 2048180486, 333721558, 2048180227, 333721559, 2048180181, 2048180224, 333721589, 2048180172, 2048180381, 333721560, 333721561, 2048180138, 2048180143, 333721590, 2048180393, 333721562, 333721563, 2048180236, 333721564, 2048180289, 333721591, 2048180379, 333721565, 2048180492, 333721566, 333721592, 2048180121, 333721567, 2048180142, 333721572, 2048180188, 333721593, 2048180389, 333721573, 2048180306, 2048180434, 333721574, 333721594, 2048180219, 333721575, 2048180482, 333721576, 2048180144, 2048180266, 333721595, 2048180295, 333721596, 333721577, 333721578, 2048180190, 333721579, 2048180251, 333721597, 2048180154, 333721598, 333721580, 333721581, 2048180107, 333721582, 4559503017, 2048180462, 333721599, 333721583, 2048180208, 333721584, 2048180135, 333721585, 2048180283, 2048180249, 333721586, 2048180488, 333721587, 2048180156, 2048180160, 333721607, 333721608, 333721609, 333721610, 178057632], "tags": {"FIXME": "Check lanes and medians.", "NHS": "yes", "hgv": "designated", "hgv:national_network": "yes", "highway": "trunk", "lanes": "2", "name": "Million Dollar Highway", "nat_name": "United States Route 550", "ref": "US 550", "source:hgv:national_network": "CDOT \"Highway Data Explorer\"", "surface": "asphalt"}}, {"type": "way", "id": 29985495, "nodes": [330098630, 2048180424, 330098632, 330098635, 330098636, 330098638, 2048180493, 330098640, 2048180129, 330098641], "tags": {"FIXME": "Check lanes and medians.", "NHS": "yes", "hgv": "designated", "hgv:national_network": "yes", "highway": "trunk", "lanes": "2", "nat_name": "United States Route 550", "ref": "US 550", "source:hgv:national_network": "CDOT \"Highway Data Explorer\"", "surface": "asphalt"}}, {"type": "way", "id": 29985497, "nodes": [330098625, 2048180375, 2048180302, 330098630], "tags": {"FIXME": "Check lanes and medians.", "NHS": "yes", "bridge": "yes", "hgv": "designated", "hgv:national_network": "yes", "highway": "trunk", "lanes": "2", "nat_name": "United States Route 550", "ref": "US 550", "source:hgv:national_network": "CDOT \"Highway Data Explorer\"", "surface": "asphalt"}}, {"type": "way", "id": 29985498, "nodes": [330098653, 1618481603, 330098680, 330098681, 330098683], "tags": {"highway": "secondary", "name": "Greene Street", "source:name": "Silverton, CO Street Overview map (http://www.colorado.gov/cs/Satellite/TownofSilverton/CBON/1251615939729)", "surface": "paved"}}, {"type": "way", "id": 29985501, "nodes": [330098669, 330098689, 330098691, 330098692, 330098693, 330098694], "tags": {"highway": "secondary_link", "oneway": "no", "surface": "paved"}}, {"type": "way", "id": 29985502, "nodes": [330098683, 330098694], "tags": {"highway": "secondary_link", "oneway": "yes", "surface": "paved"}}, {"type": "way", "id": 29985504, "nodes": [330098694, 330098702, 330098680], "tags": {"highway": "secondary_link", "oneway": "yes", "surface": "paved"}}, {"type": "way", "id": 29985505, "nodes": [330098703, 2048180458, 330098704, 330098705, 330098706], "tags": {"highway": "unclassified", "name": "Mineral Street", "surface": "unpaved"}}, {"type": "way", "id": 29985506, "nodes": [330098681, 330098708, 330098709, 330098706, 1826005507], "tags": {"highway": "residential", "name": "5th Street", "surface": "gravel"}}, {"type": "way", "id": 29985511, "nodes": [2042183459, 2042183261, 330098732, 2042183336, 5224263130, 5224263129, 5224263282, 5224263128, 330098752], "tags": {"highway": "residential", "name": "5th Street", "surface": "gravel"}}, {"type": "way", "id": 29985513, "nodes": [330098752, 5224263283, 330098758, 5224263284, 330098762, 5224263287, 5224263288, 330098756], "tags": {"highway": "residential", "name": "Snowden", "surface": "gravel"}}, {"type": "way", "id": 29985515, "nodes": [330098685, 4973035051, 2042183213, 330098741, 2042183373, 330098774, 5224263286, 5224263285, 330098756], "tags": {"highway": "residential", "name": "West 6th Street", "surface": "gravel"}}, {"type": "way", "id": 30035715, "nodes": [330764519, 2042183378, 330764520, 2042183398, 330764521], "tags": {"highway": "residential", "name": "West 7th Street", "surface": "gravel"}}, {"type": "way", "id": 30035717, "nodes": [2042183279, 5224263281, 1826005508, 2042183269, 330764522, 2042183214, 330764524, 2042183436, 330764521], "tags": {"highway": "residential", "name": "East 7th Street", "surface": "gravel"}}, {"type": "way", "id": 30035718, "nodes": [330764525, 2042183387, 330764526], "tags": {"highway": "residential", "name": "West 8th Street", "surface": "gravel"}}, {"type": "way", "id": 30035719, "nodes": [330764527, 5224263134, 330764528, 5224263133, 330764529, 5224263132, 5224263131, 2042183404, 330764530, 2042183392, 330764526], "tags": {"highway": "residential", "name": "East 8th Street", "surface": "gravel"}}, {"type": "way", "id": 30035720, "nodes": [330764542, 2042183444, 330764543], "tags": {"highway": "residential", "ref": "West 9th Street", "surface": "gravel"}}, {"type": "way", "id": 30035721, "nodes": [330764544, 5224263138, 5224263137, 330764545, 2042183454, 330764546, 2042183417, 330764547, 2042183256, 330764543], "tags": {"highway": "residential", "name": "East 9th Street", "surface": "gravel"}}, {"type": "way", "id": 30035722, "nodes": [330764549, 2042183415, 330764550, 2042183406, 330764551, 2042183368, 330764552, 3067755389, 330764553, 4626926801, 3042563878], "tags": {"highway": "residential", "name": "East 10th Street", "surface": "gravel"}}, {"type": "way", "id": 30035723, "nodes": [1826005506, 330764555], "tags": {"highway": "residential", "name": "Keystone St", "surface": "gravel"}}, {"type": "way", "id": 30035726, "nodes": [330764561, 2042183317, 330764562, 2042183401, 330764566, 2042183407, 330764567, 5224262997, 5224262996, 330764560], "tags": {"highway": "residential", "name": "West 11th Street", "surface": "gravel"}}, {"type": "way", "id": 30035728, "nodes": [330764573, 330764572, 2042183223, 330764574, 2042183411, 4973035050], "tags": {"highway": "residential", "name": "West 12th Street", "surface": "gravel"}}, {"type": "way", "id": 30035729, "nodes": [3042563270, 330764577, 330764581, 330764576, 2042183303, 4973035049], "tags": {"highway": "residential", "name": "East 12th Street", "surface": "gravel"}}, {"type": "way", "id": 30035730, "nodes": [330764577, 3067755413, 4676573324, 5224263228, 5224263227, 330764569, 5224263230, 5224263229, 330764552, 330764578, 5224263141, 5224263140, 5224263139, 330764544], "tags": {"highway": "residential", "name": "Cement Street", "surface": "gravel"}}, {"type": "way", "id": 30035731, "nodes": [330764581, 4676573326, 4676573325, 330764570, 330764551, 330764546, 330764548, 5224263136, 330764580, 5224263135, 330764527], "tags": {"highway": "residential", "name": "Mineral Street", "surface": "gravel"}}, {"type": "way", "id": 30035732, "nodes": [330764581, 330764582, 5224263147, 5224263153, 5224263148, 330764583], "tags": {"highway": "residential", "name": "Mineral Street", "surface": "gravel"}}, {"type": "way", "id": 30035733, "nodes": [330764584, 330764585, 2042183439, 330764586, 2042183257, 330764587], "tags": {"highway": "residential", "name": "West 13th Street", "surface": "gravel"}}, {"type": "way", "id": 30035734, "nodes": [330764583, 5224263149, 330764589, 5224263152, 5224263151, 5224263150, 330764590, 330764588, 2042183350, 330764587], "tags": {"highway": "residential", "name": "East 13th Street", "surface": "gravel"}}, {"type": "way", "id": 30035735, "nodes": [330764591, 2042183268, 330764592, 2042183276, 330764593, 2042183267, 330764594], "tags": {"highway": "residential", "name": "West 14th Street", "surface": "gravel"}}, {"type": "way", "id": 30035736, "nodes": [2084019368, 2084019367, 5224263143, 5224263142, 2084019366, 2084019365, 5224263146, 5224263145, 5224263144, 330764596, 330764595], "tags": {"highway": "residential", "name": "East 14th Street", "surface": "gravel"}}, {"type": "way", "id": 30035737, "nodes": [330764602, 330764588, 330764576, 330764571, 330764550], "tags": {"highway": "residential", "name": "Blair Street", "surface": "gravel"}}, {"type": "way", "id": 30035738, "nodes": [330764604, 5224262792, 5224262766, 330764605, 2042183325, 330764606], "tags": {"highway": "residential", "name": "West 15th Street", "piste:difficulty": "intermediate", "piste:grooming": "classic+skating", "piste:name": "Silverton Town Loop", "piste:type": "nordic", "surface": "gravel"}}, {"type": "way", "id": 30035739, "nodes": [330764607, 2042183339, 330764608, 2042183372, 330764609], "tags": {"highway": "residential", "name": "West 15th Street", "surface": "gravel"}}, {"type": "way", "id": 30035741, "nodes": [330764612, 2042183408, 330764613, 2042183334, 330764614], "tags": {"highway": "residential", "name": "East 15th Street", "surface": "gravel"}}, {"type": "way", "id": 30035742, "nodes": [330764615, 2042183218, 330764616, 5224263191, 2042183346, 330764617], "tags": {"highway": "residential", "name": "West 16th Street", "surface": "gravel"}}, {"type": "way", "id": 30035743, "nodes": [330764618, 2042183451, 330764619, 2042183456, 330764620, 2042183231, 330764621, 2042183371, 330764622], "tags": {"highway": "residential", "name": "East 16th Street", "surface": "gravel"}}, {"type": "way", "id": 30035744, "nodes": [330764623, 330764618, 331024444], "tags": {"highway": "secondary", "name": "Greene Street", "surface": "paved"}}, {"type": "way", "id": 30035745, "nodes": [330764624, 5224263194, 5224263193, 330764625, 330764615, 330764607, 330764606, 330764592, 330764585, 330764572, 330764566, 330764556], "tags": {"highway": "residential", "name": "Snowden Street", "surface": "gravel"}}, {"type": "way", "id": 30035746, "nodes": [330764626, 5224263196, 330764627, 330764628, 2042183331, 330764629, 5224263195, 330764624], "tags": {"highway": "residential", "name": "River Street", "surface": "gravel"}}, {"type": "way", "id": 30035747, "nodes": [330764617, 5224263190, 5224263192, 330764630, 330764608, 330764593, 330764586, 330764574, 330764562, 330764557, 330764542, 330764525, 330764520, 330098741, 330098732], "tags": {"highway": "residential", "name": "Reese Street", "surface": "gravel"}}, {"type": "way", "id": 30035748, "nodes": [330764631, 2042183281, 330764632], "tags": {"highway": "residential", "name": "East 17th Street", "surface": "gravel"}}, {"type": "way", "id": 30035749, "nodes": [330764633, 2042183381, 330764634], "tags": {"highway": "residential", "name": "East 17th Street", "surface": "gravel"}}, {"type": "way", "id": 30035750, "nodes": [330764635, 2042183426, 330764636], "tags": {"highway": "residential", "name": "East 17th Street", "surface": "gravel"}}, {"type": "way", "id": 30035751, "nodes": [330764619, 330764635, 330764634, 330764637], "tags": {"highway": "residential", "name": "Blair Street", "surface": "gravel"}}, {"type": "way", "id": 30035752, "nodes": [330764638, 2042183222, 330764639, 2042183391, 330764640, 2042183425, 330764641], "tags": {"highway": "residential", "name": "East 18th Street", "surface": "gravel"}}, {"type": "way", "id": 30035753, "nodes": [330764640, 330764633, 330764620, 330764614, 330764599], "tags": {"highway": "residential", "name": "Mineral Street", "surface": "gravel"}}, {"type": "way", "id": 30035755, "nodes": [330764643, 330764644], "tags": {"highway": "residential", "name": "East 19th Street", "surface": "gravel"}}, {"type": "way", "id": 30035756, "nodes": [330764644, 330764641, 330764631, 330764621, 330764613, 330764598, 330764603], "tags": {"highway": "residential", "name": "Cement Street", "surface": "gravel"}}, {"type": "way", "id": 30035758, "nodes": [333719480, 333719479, 333719478, 333719477, 333719476, 333719545, 7919003634, 333719474, 333719473, 333719470, 333719469, 333719468, 333719544, 333719543, 333719542, 333719467, 333719466, 333719465, 333719464, 333719463, 333719541, 333719462, 333719461, 333719460, 333719459, 333719458, 333719456, 333719454, 331058142, 331058140, 331058138, 331058136, 331058133, 2899369380, 331058131, 331058128, 2899369379, 331058127, 5224263224, 2899369381, 331058364, 2899369376, 331058126, 2899369377, 331058125, 2899369378, 331058123, 331058121, 331058119, 331058117, 331058362, 331058115, 331058113, 2042183239, 331058110, 2042183330, 330764650, 330764651, 330764652, 330764638, 9234330036, 330764653, 330764623], "tags": {"highway": "tertiary", "name": "State Highway 110A", "oneway": "no", "ref": "CO 110A", "source:name": "TIGER", "surface": "paved"}}, {"type": "way", "id": 30035759, "nodes": [330764600, 330764601], "tags": {"bridge": "yes", "highway": "residential", "name": "East 14th Street", "surface": "concrete"}}, {"type": "way", "id": 30035760, "nodes": [330764601, 2042183396, 330764602, 2042183405, 330764594], "tags": {"highway": "residential", "maxspeed": "15 mph", "name": "East 14th Street", "surface": "gravel"}}, {"type": "way", "id": 30035761, "nodes": [330764595, 330764597], "tags": {"bridge": "yes", "highway": "residential", "name": "East 14th Street"}}, {"type": "way", "id": 30035762, "nodes": [330764597, 2042183427, 330764598, 2042183301, 330764599, 330764600], "tags": {"highway": "residential", "name": "East 14th Street", "surface": "gravel"}}, {"type": "way", "id": 30053482, "nodes": [331024442, 330764609, 330764594, 330764587, 330764575, 330764561, 330764549, 330764543, 330764526, 330764521, 2048180177, 330098685, 330098683], "tags": {"highway": "secondary", "name": "Greene Street", "surface": "paved"}}, {"type": "way", "id": 30053483, "nodes": [331024444, 331024442], "tags": {"bridge": "yes", "highway": "secondary", "name": "Greene Street", "surface": "paved"}}, {"type": "way", "id": 30056886, "nodes": [331058127, 5224263225, 5224263226, 331058144], "tags": {"highway": "residential", "ref": "CR 34", "surface": "gravel"}}, {"type": "way", "id": 30056887, "nodes": [331058144, 5224263223, 5224263222, 331058125], "tags": {"highway": "residential", "ref": "CR 34", "surface": "gravel"}}, {"type": "way", "id": 30056888, "nodes": [331058146, 331058189, 331058192, 331058195, 331058197], "tags": {"highway": "residential", "surface": "gravel"}}, {"type": "way", "id": 30060941, "nodes": [331107624, 331107627, 2048180460, 2048180387, 331107628, 2048180115, 331107631, 331107634, 331107636, 331107638, 331107639, 331107641, 331107643, 331107645, 331107647, 331107652, 331107654, 331107656, 331107658, 331107660, 331107662, 331107663, 331108705, 331108706, 331108707, 331108708, 331108709, 331108710, 331108711, 331108712, 2050001958, 331108713, 2050001902, 331108714, 331108715, 331108716, 331108717, 331108718, 331108719, 331108720, 331108721, 331108722, 331108723, 3975607029, 3975607028], "tags": {"highway": "unclassified", "ref": "CR 31", "surface": "gravel"}}, {"type": "way", "id": 30106023, "nodes": [331679567, 331679568, 331679569, 331679570, 331679571, 331679573, 330764644], "tags": {"highway": "residential", "surface": "gravel"}}, {"type": "way", "id": 30106026, "nodes": [331679583, 331679567, 331058360], "tags": {"highway": "unclassified", "ref": "CR 20", "surface": "gravel"}}, {"type": "way", "id": 30279493, "nodes": [178053836, 333718019, 333718020, 333718021, 333718022, 333718023, 333718024, 333718025, 333718026, 333718029, 333718031, 333718033, 333718036, 5226032030, 333718038, 333718041, 333718043, 333718045, 333718050, 333718051, 5226028614, 333718052, 333718053, 333718054, 333718055, 333718056, 333718057, 333718058, 333718059, 333718060, 333718061, 333718062, 333718063, 333718064, 333718065, 333718066, 333718067, 333718068, 333718069, 333718070, 331058360, 331058183, 331058368, 331058357, 331058367, 331058350, 331058347, 331058345, 331058342, 331058340, 331058338, 331058333, 331058329, 330764645, 330764643, 330764646, 330764647, 330764639, 330764637, 330764648, 330764649, 2042183289, 330764636, 330764623], "tags": {"highway": "tertiary", "name": "State Highway 110", "ref": "CO 110", "surface": "paved"}}, {"type": "way", "id": 30279629, "nodes": [333719482, 2084070404, 333719481, 333719484, 333719485, 333719486, 333719487, 333719488, 333719489, 333719490, 333719491, 333719493, 333719494, 6191492208, 333719496, 333719497, 333719498, 333719499, 2048198851, 2048198954, 2048199117, 333719500, 333719501, 2048198776, 333719502, 2048198779, 333719503, 2048198897, 333719504, 333719506, 333719507, 2048198927, 2048198671, 333719510, 2048198773, 333719513, 333719516, 2048198595, 2048199284, 333719517, 2048199022, 2048199120, 333719527, 2048199419, 333719530, 2048199108, 333719534, 333719536, 2048198901, 2048199403, 333719538, 2048198720, 333719539, 333719540, 333719480], "tags": {"highway": "unclassified", "name": "State Highway 110A", "ref": "CO 110A", "source:name": "TIGER", "surface": "gravel"}}, {"type": "way", "id": 121115350, "nodes": [330098641, 1356606876, 2048180440, 2048180273, 1356606879, 7919017538, 1356606891, 1356606892], "tags": {"highway": "residential", "name": "West 3rd Street", "surface": "gravel"}}, {"type": "way", "id": 121115352, "nodes": [330098641, 330098646, 330098653, 330098658, 2048180182, 330098661, 330098663, 330098664, 330098667, 1356606892, 330098669], "tags": {"FIXME": "Check lanes and medians.", "NHS": "yes", "hgv": "designated", "hgv:national_network": "yes", "highway": "trunk", "lanes": "2", "nat_name": "United States Route 550", "ref": "US 550", "source:hgv:national_network": "CDOT \"Highway Data Explorer\"", "surface": "asphalt"}}, {"type": "way", "id": 171598671, "nodes": [3042563877, 330764569, 2042183315, 330764570, 2042183241, 330764571, 2042183342, 330764561], "tags": {"highway": "residential", "name": "East 11th Street", "surface": "gravel"}}, {"type": "way", "id": 171598672, "nodes": [331058144, 331058146, 331058149, 331058151, 331058153, 5224263197, 5224263198, 331058155, 5224263199, 331058157, 5224263200, 5224263201, 331058159, 5224263202, 5224263203, 331058162, 5224263218, 5224263221, 5224263219, 5224263220, 331058166, 5224263204, 5224263205, 331058169, 5224263206, 5224263207, 5224263208, 331058171, 5224263209, 331058173, 5224263210, 5224263211, 5224263212, 331058175, 5224263213, 331058177, 5224263214, 5224263215, 331058181, 5224263216, 5224263217, 331058183], "tags": {"highway": "residential", "ref": "CR 34", "surface": "gravel"}}, {"type": "way", "id": 193702015, "nodes": [330764555, 330764554, 2042183272, 330764556, 2042183217, 330764557, 2042183353, 330764549], "tags": {"highway": "residential", "name": "West 10th Street", "surface": "gravel"}}, {"type": "way", "id": 193702016, "nodes": [1826005504, 5224262999, 5224262998, 330764554, 330764558, 5224263000, 5224263001, 330764559, 5224262994, 5224262995, 330764560], "tags": {"highway": "residential", "name": "Bluff Street", "surface": "gravel"}}, {"type": "way", "id": 233581756, "nodes": [330764550, 330764547, 330764530, 330764524], "tags": {"highway": "residential", "name": "Empire Street", "source": "survey", "surface": "gravel"}}, {"type": "way", "id": 507877012, "nodes": [4973035050, 330764575], "tags": {"highway": "residential", "name": "West 12th Street", "surface": "asphalt"}}, {"type": "way", "id": 507877013, "nodes": [4973035049, 330764575], "tags": {"highway": "residential", "name": "East 12th Street", "surface": "asphalt"}}, {"type": "way", "id": 539953250, "nodes": [330098752, 9234256700, 5224263002, 5224263003, 5224263004, 5224263005, 5224263006, 5224263127, 5224263007, 5224263008, 5224263009, 5224263010, 5224263011, 5224263012, 5224263013, 5224263014, 5224263015, 5224263016, 5224263017, 5224263018, 5224263019, 5224263020, 5224263121, 5224263125, 5224263126, 5224263122, 5224263123, 5224263124, 5224263009], "tags": {"highway": "residential", "surface": "gravel"}}, {"type": "way", "id": 1000402254, "nodes": [3042563878, 3042563879, 3042563880, 3042563881, 3042563882, 3042563883, 3042563884, 3042563885, 3042563886, 3042563887, 3042563888], "tags": {"highway": "residential", "name": "East 10th Street", "piste:difficulty": "easy", "piste:grooming": "classic+skating", "piste:name": "Silverton Town Loop", "piste:type": "nordic", "surface": "gravel"}}]}